[
    {
        "text": "p5.js arc()",
        "link": "https://p5js.org/reference/p5/arc/"
    },
    {
        "text": "p5.js circle()",
        "link": "https://p5js.org/reference/p5/circle/"
    },
    {
        "text": "p5.js ellipse()",
        "link": "https://p5js.org/reference/p5/ellipse/"
    },
    {
        "text": "p5.js line()",
        "link": "https://p5js.org/reference/p5/line/"
    },
    {
        "text": "p5.js point()",
        "link": "https://p5js.org/reference/p5/point/"
    },
    {
        "text": "p5.js quad()",
        "link": "https://p5js.org/reference/p5/quad/"
    },
    {
        "text": "p5.js rect()",
        "link": "https://p5js.org/reference/p5/rect/"
    },
    {
        "text": "p5.js square()",
        "link": "https://p5js.org/reference/p5/square/"
    },
    {
        "text": "p5.js triangle()",
        "link": "https://p5js.org/reference/p5/triangle/"
    },
    {
        "text": "p5.js createModel()",
        "link": "https://p5js.org/reference/p5/createModel/"
    },
    {
        "text": "p5.js loadModel()",
        "link": "https://p5js.org/reference/p5/loadModel/"
    },
    {
        "text": "p5.js model()",
        "link": "https://p5js.org/reference/p5/model/"
    },
    {
        "text": "p5.js beginGeometry()",
        "link": "https://p5js.org/reference/p5/beginGeometry/"
    },
    {
        "text": "p5.js box()",
        "link": "https://p5js.org/reference/p5/box/"
    },
    {
        "text": "p5.js buildGeometry()",
        "link": "https://p5js.org/reference/p5/buildGeometry/"
    },
    {
        "text": "p5.js cone()",
        "link": "https://p5js.org/reference/p5/cone/"
    },
    {
        "text": "p5.js cylinder()",
        "link": "https://p5js.org/reference/p5/cylinder/"
    },
    {
        "text": "p5.js ellipsoid()",
        "link": "https://p5js.org/reference/p5/ellipsoid/"
    },
    {
        "text": "p5.js endGeometry()",
        "link": "https://p5js.org/reference/p5/endGeometry/"
    },
    {
        "text": "p5.js freeGeometry()",
        "link": "https://p5js.org/reference/p5/freeGeometry/"
    },
    {
        "text": "p5.js plane()",
        "link": "https://p5js.org/reference/p5/plane/"
    },
    {
        "text": "p5.js sphere()",
        "link": "https://p5js.org/reference/p5/sphere/"
    },
    {
        "text": "p5.js torus()",
        "link": "https://p5js.org/reference/p5/torus/"
    },
    {
        "text": "p5.js ellipseMode()",
        "link": "https://p5js.org/reference/p5/ellipseMode/"
    },
    {
        "text": "p5.js noSmooth()",
        "link": "https://p5js.org/reference/p5/noSmooth/"
    },
    {
        "text": "p5.js rectMode()",
        "link": "https://p5js.org/reference/p5/rectMode/"
    },
    {
        "text": "p5.js smooth()",
        "link": "https://p5js.org/reference/p5/smooth/"
    },
    {
        "text": "p5.js strokeCap()",
        "link": "https://p5js.org/reference/p5/strokeCap/"
    },
    {
        "text": "p5.js strokeJoin()",
        "link": "https://p5js.org/reference/p5/strokeJoin/"
    },
    {
        "text": "p5.js strokeWeight()",
        "link": "https://p5js.org/reference/p5/strokeWeight/"
    },
    {
        "text": "p5.js bezier()",
        "link": "https://p5js.org/reference/p5/bezier/"
    },
    {
        "text": "p5.js bezierDetail()",
        "link": "https://p5js.org/reference/p5/bezierDetail/"
    },
    {
        "text": "p5.js bezierPoint()",
        "link": "https://p5js.org/reference/p5/bezierPoint/"
    },
    {
        "text": "p5.js bezierTangent()",
        "link": "https://p5js.org/reference/p5/bezierTangent/"
    },
    {
        "text": "p5.js curve()",
        "link": "https://p5js.org/reference/p5/curve/"
    },
    {
        "text": "p5.js curveDetail()",
        "link": "https://p5js.org/reference/p5/curveDetail/"
    },
    {
        "text": "p5.js curvePoint()",
        "link": "https://p5js.org/reference/p5/curvePoint/"
    },
    {
        "text": "p5.js curveTangent()",
        "link": "https://p5js.org/reference/p5/curveTangent/"
    },
    {
        "text": "p5.js curveTightness()",
        "link": "https://p5js.org/reference/p5/curveTightness/"
    },
    {
        "text": "p5.js beginContour()",
        "link": "https://p5js.org/reference/p5/beginContour/"
    },
    {
        "text": "p5.js beginShape()",
        "link": "https://p5js.org/reference/p5/beginShape/"
    },
    {
        "text": "p5.js bezierVertex()",
        "link": "https://p5js.org/reference/p5/bezierVertex/"
    },
    {
        "text": "p5.js curveVertex()",
        "link": "https://p5js.org/reference/p5/curveVertex/"
    },
    {
        "text": "p5.js endContour()",
        "link": "https://p5js.org/reference/p5/endContour/"
    },
    {
        "text": "p5.js endShape()",
        "link": "https://p5js.org/reference/p5/endShape/"
    },
    {
        "text": "p5.js normal()",
        "link": "https://p5js.org/reference/p5/normal/"
    },
    {
        "text": "p5.js quadraticVertex()",
        "link": "https://p5js.org/reference/p5/quadraticVertex/"
    },
    {
        "text": "p5.js vertex()",
        "link": "https://p5js.org/reference/p5/vertex/"
    },
    {
        "text": "p5.js calculateBoundingBox()",
        "link": "https://p5js.org/reference/p5.Geometry/calculateBoundingBox/"
    },
    {
        "text": "p5.js clearColors()",
        "link": "https://p5js.org/reference/p5.Geometry/clearColors/"
    },
    {
        "text": "p5.js computeFaces()",
        "link": "https://p5js.org/reference/p5.Geometry/computeFaces/"
    },
    {
        "text": "p5.js computeNormals()",
        "link": "https://p5js.org/reference/p5.Geometry/computeNormals/"
    },
    {
        "text": "p5.js faces",
        "link": "https://p5js.org/reference/p5.Geometry/faces/"
    },
    {
        "text": "p5.js flipU()",
        "link": "https://p5js.org/reference/p5.Geometry/flipU/"
    },
    {
        "text": "p5.js flipV()",
        "link": "https://p5js.org/reference/p5.Geometry/flipV/"
    },
    {
        "text": "p5.js normalize()",
        "link": "https://p5js.org/reference/p5.Geometry/normalize/"
    },
    {
        "text": "p5.js saveObj()",
        "link": "https://p5js.org/reference/p5.Geometry/saveObj/"
    },
    {
        "text": "p5.js saveStl()",
        "link": "https://p5js.org/reference/p5.Geometry/saveStl/"
    },
    {
        "text": "p5.js uvs",
        "link": "https://p5js.org/reference/p5.Geometry/uvs/"
    },
    {
        "text": "p5.js vertexNormals",
        "link": "https://p5js.org/reference/p5.Geometry/vertexNormals/"
    },
    {
        "text": "p5.js vertices",
        "link": "https://p5js.org/reference/p5.Geometry/vertices/"
    },
    {
        "text": "p5.js alpha()",
        "link": "https://p5js.org/reference/p5/alpha/"
    },
    {
        "text": "p5.js blue()",
        "link": "https://p5js.org/reference/p5/blue/"
    },
    {
        "text": "p5.js brightness()",
        "link": "https://p5js.org/reference/p5/brightness/"
    },
    {
        "text": "p5.js color()",
        "link": "https://p5js.org/reference/p5/color/"
    },
    {
        "text": "p5.js green()",
        "link": "https://p5js.org/reference/p5/green/"
    },
    {
        "text": "p5.js hue()",
        "link": "https://p5js.org/reference/p5/hue/"
    },
    {
        "text": "p5.js lerpColor()",
        "link": "https://p5js.org/reference/p5/lerpColor/"
    },
    {
        "text": "p5.js lightness()",
        "link": "https://p5js.org/reference/p5/lightness/"
    },
    {
        "text": "p5.js paletteLerp()",
        "link": "https://p5js.org/reference/p5/paletteLerp/"
    },
    {
        "text": "p5.js red()",
        "link": "https://p5js.org/reference/p5/red/"
    },
    {
        "text": "p5.js saturation()",
        "link": "https://p5js.org/reference/p5/saturation/"
    },
    {
        "text": "p5.js background()",
        "link": "https://p5js.org/reference/p5/background/"
    },
    {
        "text": "p5.js beginClip()",
        "link": "https://p5js.org/reference/p5/beginClip/"
    },
    {
        "text": "p5.js clear()",
        "link": "https://p5js.org/reference/p5/clear/"
    },
    {
        "text": "p5.js clip()",
        "link": "https://p5js.org/reference/p5/clip/"
    },
    {
        "text": "p5.js colorMode()",
        "link": "https://p5js.org/reference/p5/colorMode/"
    },
    {
        "text": "p5.js endClip()",
        "link": "https://p5js.org/reference/p5/endClip/"
    },
    {
        "text": "p5.js erase()",
        "link": "https://p5js.org/reference/p5/erase/"
    },
    {
        "text": "p5.js fill()",
        "link": "https://p5js.org/reference/p5/fill/"
    },
    {
        "text": "p5.js noErase()",
        "link": "https://p5js.org/reference/p5/noErase/"
    },
    {
        "text": "p5.js noFill()",
        "link": "https://p5js.org/reference/p5/noFill/"
    },
    {
        "text": "p5.js noStroke()",
        "link": "https://p5js.org/reference/p5/noStroke/"
    },
    {
        "text": "p5.js stroke()",
        "link": "https://p5js.org/reference/p5/stroke/"
    },
    {
        "text": "p5.js setAlpha()",
        "link": "https://p5js.org/reference/p5.Color/setAlpha/"
    },
    {
        "text": "p5.js setBlue()",
        "link": "https://p5js.org/reference/p5.Color/setBlue/"
    },
    {
        "text": "p5.js setGreen()",
        "link": "https://p5js.org/reference/p5.Color/setGreen/"
    },
    {
        "text": "p5.js setRed()",
        "link": "https://p5js.org/reference/p5.Color/setRed/"
    },
    {
        "text": "p5.js toString()",
        "link": "https://p5js.org/reference/p5.Color/toString/"
    },
    {
        "text": "p5.js textAlign()",
        "link": "https://p5js.org/reference/p5/textAlign/"
    },
    {
        "text": "p5.js textAscent()",
        "link": "https://p5js.org/reference/p5/textAscent/"
    },
    {
        "text": "p5.js textDescent()",
        "link": "https://p5js.org/reference/p5/textDescent/"
    },
    {
        "text": "p5.js textLeading()",
        "link": "https://p5js.org/reference/p5/textLeading/"
    },
    {
        "text": "p5.js textSize()",
        "link": "https://p5js.org/reference/p5/textSize/"
    },
    {
        "text": "p5.js textStyle()",
        "link": "https://p5js.org/reference/p5/textStyle/"
    },
    {
        "text": "p5.js textWidth()",
        "link": "https://p5js.org/reference/p5/textWidth/"
    },
    {
        "text": "p5.js textWrap()",
        "link": "https://p5js.org/reference/p5/textWrap/"
    },
    {
        "text": "p5.js loadFont()",
        "link": "https://p5js.org/reference/p5/loadFont/"
    },
    {
        "text": "p5.js text()",
        "link": "https://p5js.org/reference/p5/text/"
    },
    {
        "text": "p5.js textFont()",
        "link": "https://p5js.org/reference/p5/textFont/"
    },
    {
        "text": "p5.js font",
        "link": "https://p5js.org/reference/p5.Font/font/"
    },
    {
        "text": "p5.js textBounds()",
        "link": "https://p5js.org/reference/p5.Font/textBounds/"
    },
    {
        "text": "p5.js textToPoints()",
        "link": "https://p5js.org/reference/p5.Font/textToPoints/"
    },
    {
        "text": "p5.js createImage()",
        "link": "https://p5js.org/reference/p5/createImage/"
    },
    {
        "text": "p5.js saveCanvas()",
        "link": "https://p5js.org/reference/p5/saveCanvas/"
    },
    {
        "text": "p5.js saveFrames()",
        "link": "https://p5js.org/reference/p5/saveFrames/"
    },
    {
        "text": "p5.js image()",
        "link": "https://p5js.org/reference/p5/image/"
    },
    {
        "text": "p5.js imageMode()",
        "link": "https://p5js.org/reference/p5/imageMode/"
    },
    {
        "text": "p5.js loadImage()",
        "link": "https://p5js.org/reference/p5/loadImage/"
    },
    {
        "text": "p5.js noTint()",
        "link": "https://p5js.org/reference/p5/noTint/"
    },
    {
        "text": "p5.js saveGif()",
        "link": "https://p5js.org/reference/p5/saveGif/"
    },
    {
        "text": "p5.js tint()",
        "link": "https://p5js.org/reference/p5/tint/"
    },
    {
        "text": "p5.js blend()",
        "link": "https://p5js.org/reference/p5/blend/"
    },
    {
        "text": "p5.js copy()",
        "link": "https://p5js.org/reference/p5/copy/"
    },
    {
        "text": "p5.js filter()",
        "link": "https://p5js.org/reference/p5/filter/"
    },
    {
        "text": "p5.js get()",
        "link": "https://p5js.org/reference/p5/get/"
    },
    {
        "text": "p5.js loadPixels()",
        "link": "https://p5js.org/reference/p5/loadPixels/"
    },
    {
        "text": "p5.js pixels",
        "link": "https://p5js.org/reference/p5/pixels/"
    },
    {
        "text": "p5.js set()",
        "link": "https://p5js.org/reference/p5/set/"
    },
    {
        "text": "p5.js updatePixels()",
        "link": "https://p5js.org/reference/p5/updatePixels/"
    },
    {
        "text": "p5.js blend()",
        "link": "https://p5js.org/reference/p5.Image/blend/"
    },
    {
        "text": "p5.js copy()",
        "link": "https://p5js.org/reference/p5.Image/copy/"
    },
    {
        "text": "p5.js delay()",
        "link": "https://p5js.org/reference/p5.Image/delay/"
    },
    {
        "text": "p5.js filter()",
        "link": "https://p5js.org/reference/p5.Image/filter/"
    },
    {
        "text": "p5.js get()",
        "link": "https://p5js.org/reference/p5.Image/get/"
    },
    {
        "text": "p5.js getCurrentFrame()",
        "link": "https://p5js.org/reference/p5.Image/getCurrentFrame/"
    },
    {
        "text": "p5.js height",
        "link": "https://p5js.org/reference/p5.Image/height/"
    },
    {
        "text": "p5.js loadPixels()",
        "link": "https://p5js.org/reference/p5.Image/loadPixels/"
    },
    {
        "text": "p5.js mask()",
        "link": "https://p5js.org/reference/p5.Image/mask/"
    },
    {
        "text": "p5.js numFrames()",
        "link": "https://p5js.org/reference/p5.Image/numFrames/"
    },
    {
        "text": "p5.js pause()",
        "link": "https://p5js.org/reference/p5.Image/pause/"
    },
    {
        "text": "p5.js pixelDensity()",
        "link": "https://p5js.org/reference/p5.Image/pixelDensity/"
    },
    {
        "text": "p5.js pixels",
        "link": "https://p5js.org/reference/p5.Image/pixels/"
    },
    {
        "text": "p5.js play()",
        "link": "https://p5js.org/reference/p5.Image/play/"
    },
    {
        "text": "p5.js reset()",
        "link": "https://p5js.org/reference/p5.Image/reset/"
    },
    {
        "text": "p5.js resize()",
        "link": "https://p5js.org/reference/p5.Image/resize/"
    },
    {
        "text": "p5.js save()",
        "link": "https://p5js.org/reference/p5.Image/save/"
    },
    {
        "text": "p5.js set()",
        "link": "https://p5js.org/reference/p5.Image/set/"
    },
    {
        "text": "p5.js setFrame()",
        "link": "https://p5js.org/reference/p5.Image/setFrame/"
    },
    {
        "text": "p5.js updatePixels()",
        "link": "https://p5js.org/reference/p5.Image/updatePixels/"
    },
    {
        "text": "p5.js width",
        "link": "https://p5js.org/reference/p5.Image/width/"
    },
    {
        "text": "p5.js applyMatrix()",
        "link": "https://p5js.org/reference/p5/applyMatrix/"
    },
    {
        "text": "p5.js resetMatrix()",
        "link": "https://p5js.org/reference/p5/resetMatrix/"
    },
    {
        "text": "p5.js rotate()",
        "link": "https://p5js.org/reference/p5/rotate/"
    },
    {
        "text": "p5.js rotateX()",
        "link": "https://p5js.org/reference/p5/rotateX/"
    },
    {
        "text": "p5.js rotateY()",
        "link": "https://p5js.org/reference/p5/rotateY/"
    },
    {
        "text": "p5.js rotateZ()",
        "link": "https://p5js.org/reference/p5/rotateZ/"
    },
    {
        "text": "p5.js scale()",
        "link": "https://p5js.org/reference/p5/scale/"
    },
    {
        "text": "p5.js shearX()",
        "link": "https://p5js.org/reference/p5/shearX/"
    },
    {
        "text": "p5.js shearY()",
        "link": "https://p5js.org/reference/p5/shearY/"
    },
    {
        "text": "p5.js translate()",
        "link": "https://p5js.org/reference/p5/translate/"
    },
    {
        "text": "p5.js cursor()",
        "link": "https://p5js.org/reference/p5/cursor/"
    },
    {
        "text": "p5.js deltaTime",
        "link": "https://p5js.org/reference/p5/deltaTime/"
    },
    {
        "text": "p5.js describe()",
        "link": "https://p5js.org/reference/p5/describe/"
    },
    {
        "text": "p5.js describeElement()",
        "link": "https://p5js.org/reference/p5/describeElement/"
    },
    {
        "text": "p5.js displayDensity()",
        "link": "https://p5js.org/reference/p5/displayDensity/"
    },
    {
        "text": "p5.js displayHeight",
        "link": "https://p5js.org/reference/p5/displayHeight/"
    },
    {
        "text": "p5.js displayWidth",
        "link": "https://p5js.org/reference/p5/displayWidth/"
    },
    {
        "text": "p5.js focused",
        "link": "https://p5js.org/reference/p5/focused/"
    },
    {
        "text": "p5.js frameCount",
        "link": "https://p5js.org/reference/p5/frameCount/"
    },
    {
        "text": "p5.js frameRate()",
        "link": "https://p5js.org/reference/p5/frameRate/"
    },
    {
        "text": "p5.js fullscreen()",
        "link": "https://p5js.org/reference/p5/fullscreen/"
    },
    {
        "text": "p5.js getTargetFrameRate()",
        "link": "https://p5js.org/reference/p5/getTargetFrameRate/"
    },
    {
        "text": "p5.js getURL()",
        "link": "https://p5js.org/reference/p5/getURL/"
    },
    {
        "text": "p5.js getURLParams()",
        "link": "https://p5js.org/reference/p5/getURLParams/"
    },
    {
        "text": "p5.js getURLPath()",
        "link": "https://p5js.org/reference/p5/getURLPath/"
    },
    {
        "text": "p5.js gridOutput()",
        "link": "https://p5js.org/reference/p5/gridOutput/"
    },
    {
        "text": "p5.js height",
        "link": "https://p5js.org/reference/p5/height/"
    },
    {
        "text": "p5.js noCursor()",
        "link": "https://p5js.org/reference/p5/noCursor/"
    },
    {
        "text": "p5.js pixelDensity()",
        "link": "https://p5js.org/reference/p5/pixelDensity/"
    },
    {
        "text": "p5.js print()",
        "link": "https://p5js.org/reference/p5/print/"
    },
    {
        "text": "p5.js textOutput()",
        "link": "https://p5js.org/reference/p5/textOutput/"
    },
    {
        "text": "p5.js webglVersion",
        "link": "https://p5js.org/reference/p5/webglVersion/"
    },
    {
        "text": "p5.js width",
        "link": "https://p5js.org/reference/p5/width/"
    },
    {
        "text": "p5.js windowHeight",
        "link": "https://p5js.org/reference/p5/windowHeight/"
    },
    {
        "text": "p5.js windowResized()",
        "link": "https://p5js.org/reference/p5/windowResized/"
    },
    {
        "text": "p5.js windowWidth",
        "link": "https://p5js.org/reference/p5/windowWidth/"
    },
    {
        "text": "p5.js camera()",
        "link": "https://p5js.org/reference/p5/camera/"
    },
    {
        "text": "p5.js createCamera()",
        "link": "https://p5js.org/reference/p5/createCamera/"
    },
    {
        "text": "p5.js frustum()",
        "link": "https://p5js.org/reference/p5/frustum/"
    },
    {
        "text": "p5.js linePerspective()",
        "link": "https://p5js.org/reference/p5/linePerspective/"
    },
    {
        "text": "p5.js ortho()",
        "link": "https://p5js.org/reference/p5/ortho/"
    },
    {
        "text": "p5.js perspective()",
        "link": "https://p5js.org/reference/p5/perspective/"
    },
    {
        "text": "p5.js setCamera()",
        "link": "https://p5js.org/reference/p5/setCamera/"
    },
    {
        "text": "p5.js debugMode()",
        "link": "https://p5js.org/reference/p5/debugMode/"
    },
    {
        "text": "p5.js noDebugMode()",
        "link": "https://p5js.org/reference/p5/noDebugMode/"
    },
    {
        "text": "p5.js orbitControl()",
        "link": "https://p5js.org/reference/p5/orbitControl/"
    },
    {
        "text": "p5.js ambientLight()",
        "link": "https://p5js.org/reference/p5/ambientLight/"
    },
    {
        "text": "p5.js directionalLight()",
        "link": "https://p5js.org/reference/p5/directionalLight/"
    },
    {
        "text": "p5.js imageLight()",
        "link": "https://p5js.org/reference/p5/imageLight/"
    },
    {
        "text": "p5.js lightFalloff()",
        "link": "https://p5js.org/reference/p5/lightFalloff/"
    },
    {
        "text": "p5.js lights()",
        "link": "https://p5js.org/reference/p5/lights/"
    },
    {
        "text": "p5.js noLights()",
        "link": "https://p5js.org/reference/p5/noLights/"
    },
    {
        "text": "p5.js panorama()",
        "link": "https://p5js.org/reference/p5/panorama/"
    },
    {
        "text": "p5.js pointLight()",
        "link": "https://p5js.org/reference/p5/pointLight/"
    },
    {
        "text": "p5.js specularColor()",
        "link": "https://p5js.org/reference/p5/specularColor/"
    },
    {
        "text": "p5.js spotLight()",
        "link": "https://p5js.org/reference/p5/spotLight/"
    },
    {
        "text": "p5.js ambientMaterial()",
        "link": "https://p5js.org/reference/p5/ambientMaterial/"
    },
    {
        "text": "p5.js baseColorShader()",
        "link": "https://p5js.org/reference/p5/baseColorShader/"
    },
    {
        "text": "p5.js baseMaterialShader()",
        "link": "https://p5js.org/reference/p5/baseMaterialShader/"
    },
    {
        "text": "p5.js baseNormalShader()",
        "link": "https://p5js.org/reference/p5/baseNormalShader/"
    },
    {
        "text": "p5.js baseStrokeShader()",
        "link": "https://p5js.org/reference/p5/baseStrokeShader/"
    },
    {
        "text": "p5.js createFilterShader()",
        "link": "https://p5js.org/reference/p5/createFilterShader/"
    },
    {
        "text": "p5.js createShader()",
        "link": "https://p5js.org/reference/p5/createShader/"
    },
    {
        "text": "p5.js emissiveMaterial()",
        "link": "https://p5js.org/reference/p5/emissiveMaterial/"
    },
    {
        "text": "p5.js loadShader()",
        "link": "https://p5js.org/reference/p5/loadShader/"
    },
    {
        "text": "p5.js metalness()",
        "link": "https://p5js.org/reference/p5/metalness/"
    },
    {
        "text": "p5.js normalMaterial()",
        "link": "https://p5js.org/reference/p5/normalMaterial/"
    },
    {
        "text": "p5.js resetShader()",
        "link": "https://p5js.org/reference/p5/resetShader/"
    },
    {
        "text": "p5.js shader()",
        "link": "https://p5js.org/reference/p5/shader/"
    },
    {
        "text": "p5.js shininess()",
        "link": "https://p5js.org/reference/p5/shininess/"
    },
    {
        "text": "p5.js specularMaterial()",
        "link": "https://p5js.org/reference/p5/specularMaterial/"
    },
    {
        "text": "p5.js texture()",
        "link": "https://p5js.org/reference/p5/texture/"
    },
    {
        "text": "p5.js textureMode()",
        "link": "https://p5js.org/reference/p5/textureMode/"
    },
    {
        "text": "p5.js textureWrap()",
        "link": "https://p5js.org/reference/p5/textureWrap/"
    },
    {
        "text": "p5.js camera()",
        "link": "https://p5js.org/reference/p5.Camera/camera/"
    },
    {
        "text": "p5.js centerX",
        "link": "https://p5js.org/reference/p5.Camera/centerX/"
    },
    {
        "text": "p5.js centerY",
        "link": "https://p5js.org/reference/p5.Camera/centerY/"
    },
    {
        "text": "p5.js centerZ",
        "link": "https://p5js.org/reference/p5.Camera/centerZ/"
    },
    {
        "text": "p5.js eyeX",
        "link": "https://p5js.org/reference/p5.Camera/eyeX/"
    },
    {
        "text": "p5.js eyeY",
        "link": "https://p5js.org/reference/p5.Camera/eyeY/"
    },
    {
        "text": "p5.js eyeZ",
        "link": "https://p5js.org/reference/p5.Camera/eyeZ/"
    },
    {
        "text": "p5.js frustum()",
        "link": "https://p5js.org/reference/p5.Camera/frustum/"
    },
    {
        "text": "p5.js lookAt()",
        "link": "https://p5js.org/reference/p5.Camera/lookAt/"
    },
    {
        "text": "p5.js move()",
        "link": "https://p5js.org/reference/p5.Camera/move/"
    },
    {
        "text": "p5.js ortho()",
        "link": "https://p5js.org/reference/p5.Camera/ortho/"
    },
    {
        "text": "p5.js pan()",
        "link": "https://p5js.org/reference/p5.Camera/pan/"
    },
    {
        "text": "p5.js perspective()",
        "link": "https://p5js.org/reference/p5.Camera/perspective/"
    },
    {
        "text": "p5.js roll()",
        "link": "https://p5js.org/reference/p5.Camera/roll/"
    },
    {
        "text": "p5.js set()",
        "link": "https://p5js.org/reference/p5.Camera/set/"
    },
    {
        "text": "p5.js setPosition()",
        "link": "https://p5js.org/reference/p5.Camera/setPosition/"
    },
    {
        "text": "p5.js slerp()",
        "link": "https://p5js.org/reference/p5.Camera/slerp/"
    },
    {
        "text": "p5.js tilt()",
        "link": "https://p5js.org/reference/p5.Camera/tilt/"
    },
    {
        "text": "p5.js upX",
        "link": "https://p5js.org/reference/p5.Camera/upX/"
    },
    {
        "text": "p5.js upY",
        "link": "https://p5js.org/reference/p5.Camera/upY/"
    },
    {
        "text": "p5.js upZ",
        "link": "https://p5js.org/reference/p5.Camera/upZ/"
    },
    {
        "text": "p5.js copyToContext()",
        "link": "https://p5js.org/reference/p5.Shader/copyToContext/"
    },
    {
        "text": "p5.js inspectHooks()",
        "link": "https://p5js.org/reference/p5.Shader/inspectHooks/"
    },
    {
        "text": "p5.js modify()",
        "link": "https://p5js.org/reference/p5.Shader/modify/"
    },
    {
        "text": "p5.js setUniform()",
        "link": "https://p5js.org/reference/p5.Shader/setUniform/"
    },
    {
        "text": "p5.js blendMode()",
        "link": "https://p5js.org/reference/p5/blendMode/"
    },
    {
        "text": "p5.js clearDepth()",
        "link": "https://p5js.org/reference/p5/clearDepth/"
    },
    {
        "text": "p5.js createCanvas()",
        "link": "https://p5js.org/reference/p5/createCanvas/"
    },
    {
        "text": "p5.js createFramebuffer()",
        "link": "https://p5js.org/reference/p5/createFramebuffer/"
    },
    {
        "text": "p5.js createGraphics()",
        "link": "https://p5js.org/reference/p5/createGraphics/"
    },
    {
        "text": "p5.js drawingContext",
        "link": "https://p5js.org/reference/p5/drawingContext/"
    },
    {
        "text": "p5.js noCanvas()",
        "link": "https://p5js.org/reference/p5/noCanvas/"
    },
    {
        "text": "p5.js resizeCanvas()",
        "link": "https://p5js.org/reference/p5/resizeCanvas/"
    },
    {
        "text": "p5.js setAttributes()",
        "link": "https://p5js.org/reference/p5/setAttributes/"
    },
    {
        "text": "p5.js autoSized()",
        "link": "https://p5js.org/reference/p5.Framebuffer/autoSized/"
    },
    {
        "text": "p5.js begin()",
        "link": "https://p5js.org/reference/p5.Framebuffer/begin/"
    },
    {
        "text": "p5.js color",
        "link": "https://p5js.org/reference/p5.Framebuffer/color/"
    },
    {
        "text": "p5.js createCamera()",
        "link": "https://p5js.org/reference/p5.Framebuffer/createCamera/"
    },
    {
        "text": "p5.js depth",
        "link": "https://p5js.org/reference/p5.Framebuffer/depth/"
    },
    {
        "text": "p5.js draw()",
        "link": "https://p5js.org/reference/p5.Framebuffer/draw/"
    },
    {
        "text": "p5.js end()",
        "link": "https://p5js.org/reference/p5.Framebuffer/end/"
    },
    {
        "text": "p5.js get()",
        "link": "https://p5js.org/reference/p5.Framebuffer/get/"
    },
    {
        "text": "p5.js loadPixels()",
        "link": "https://p5js.org/reference/p5.Framebuffer/loadPixels/"
    },
    {
        "text": "p5.js pixelDensity()",
        "link": "https://p5js.org/reference/p5.Framebuffer/pixelDensity/"
    },
    {
        "text": "p5.js pixels",
        "link": "https://p5js.org/reference/p5.Framebuffer/pixels/"
    },
    {
        "text": "p5.js remove()",
        "link": "https://p5js.org/reference/p5.Framebuffer/remove/"
    },
    {
        "text": "p5.js resize()",
        "link": "https://p5js.org/reference/p5.Framebuffer/resize/"
    },
    {
        "text": "p5.js updatePixels()",
        "link": "https://p5js.org/reference/p5.Framebuffer/updatePixels/"
    },
    {
        "text": "p5.js createFramebuffer()",
        "link": "https://p5js.org/reference/p5.Graphics/createFramebuffer/"
    },
    {
        "text": "p5.js remove()",
        "link": "https://p5js.org/reference/p5.Graphics/remove/"
    },
    {
        "text": "p5.js reset()",
        "link": "https://p5js.org/reference/p5.Graphics/reset/"
    },
    {
        "text": "p5.js abs()",
        "link": "https://p5js.org/reference/p5/abs/"
    },
    {
        "text": "p5.js ceil()",
        "link": "https://p5js.org/reference/p5/ceil/"
    },
    {
        "text": "p5.js constrain()",
        "link": "https://p5js.org/reference/p5/constrain/"
    },
    {
        "text": "p5.js dist()",
        "link": "https://p5js.org/reference/p5/dist/"
    },
    {
        "text": "p5.js exp()",
        "link": "https://p5js.org/reference/p5/exp/"
    },
    {
        "text": "p5.js floor()",
        "link": "https://p5js.org/reference/p5/floor/"
    },
    {
        "text": "p5.js fract()",
        "link": "https://p5js.org/reference/p5/fract/"
    },
    {
        "text": "p5.js lerp()",
        "link": "https://p5js.org/reference/p5/lerp/"
    },
    {
        "text": "p5.js log()",
        "link": "https://p5js.org/reference/p5/log/"
    },
    {
        "text": "p5.js mag()",
        "link": "https://p5js.org/reference/p5/mag/"
    },
    {
        "text": "p5.js map()",
        "link": "https://p5js.org/reference/p5/map/"
    },
    {
        "text": "p5.js max()",
        "link": "https://p5js.org/reference/p5/max/"
    },
    {
        "text": "p5.js min()",
        "link": "https://p5js.org/reference/p5/min/"
    },
    {
        "text": "p5.js norm()",
        "link": "https://p5js.org/reference/p5/norm/"
    },
    {
        "text": "p5.js pow()",
        "link": "https://p5js.org/reference/p5/pow/"
    },
    {
        "text": "p5.js round()",
        "link": "https://p5js.org/reference/p5/round/"
    },
    {
        "text": "p5.js sq()",
        "link": "https://p5js.org/reference/p5/sq/"
    },
    {
        "text": "p5.js sqrt()",
        "link": "https://p5js.org/reference/p5/sqrt/"
    },
    {
        "text": "p5.js noise()",
        "link": "https://p5js.org/reference/p5/noise/"
    },
    {
        "text": "p5.js noiseDetail()",
        "link": "https://p5js.org/reference/p5/noiseDetail/"
    },
    {
        "text": "p5.js noiseSeed()",
        "link": "https://p5js.org/reference/p5/noiseSeed/"
    },
    {
        "text": "p5.js random()",
        "link": "https://p5js.org/reference/p5/random/"
    },
    {
        "text": "p5.js randomGaussian()",
        "link": "https://p5js.org/reference/p5/randomGaussian/"
    },
    {
        "text": "p5.js randomSeed()",
        "link": "https://p5js.org/reference/p5/randomSeed/"
    },
    {
        "text": "p5.js acos()",
        "link": "https://p5js.org/reference/p5/acos/"
    },
    {
        "text": "p5.js angleMode()",
        "link": "https://p5js.org/reference/p5/angleMode/"
    },
    {
        "text": "p5.js asin()",
        "link": "https://p5js.org/reference/p5/asin/"
    },
    {
        "text": "p5.js atan()",
        "link": "https://p5js.org/reference/p5/atan/"
    },
    {
        "text": "p5.js atan2()",
        "link": "https://p5js.org/reference/p5/atan2/"
    },
    {
        "text": "p5.js cos()",
        "link": "https://p5js.org/reference/p5/cos/"
    },
    {
        "text": "p5.js degrees()",
        "link": "https://p5js.org/reference/p5/degrees/"
    },
    {
        "text": "p5.js radians()",
        "link": "https://p5js.org/reference/p5/radians/"
    },
    {
        "text": "p5.js sin()",
        "link": "https://p5js.org/reference/p5/sin/"
    },
    {
        "text": "p5.js tan()",
        "link": "https://p5js.org/reference/p5/tan/"
    },
    {
        "text": "p5.js createVector()",
        "link": "https://p5js.org/reference/p5/createVector/"
    },
    {
        "text": "p5.js add()",
        "link": "https://p5js.org/reference/p5.Vector/add/"
    },
    {
        "text": "p5.js angleBetween()",
        "link": "https://p5js.org/reference/p5.Vector/angleBetween/"
    },
    {
        "text": "p5.js array()",
        "link": "https://p5js.org/reference/p5.Vector/array/"
    },
    {
        "text": "p5.js clampToZero()",
        "link": "https://p5js.org/reference/p5.Vector/clampToZero/"
    },
    {
        "text": "p5.js copy()",
        "link": "https://p5js.org/reference/p5.Vector/copy/"
    },
    {
        "text": "p5.js cross()",
        "link": "https://p5js.org/reference/p5.Vector/cross/"
    },
    {
        "text": "p5.js dist()",
        "link": "https://p5js.org/reference/p5.Vector/dist/"
    },
    {
        "text": "p5.js div()",
        "link": "https://p5js.org/reference/p5.Vector/div/"
    },
    {
        "text": "p5.js dot()",
        "link": "https://p5js.org/reference/p5.Vector/dot/"
    },
    {
        "text": "p5.js equals()",
        "link": "https://p5js.org/reference/p5.Vector/equals/"
    },
    {
        "text": "p5.js fromAngle()",
        "link": "https://p5js.org/reference/p5.Vector/fromAngle/"
    },
    {
        "text": "p5.js fromAngles()",
        "link": "https://p5js.org/reference/p5.Vector/fromAngles/"
    },
    {
        "text": "p5.js heading()",
        "link": "https://p5js.org/reference/p5.Vector/heading/"
    },
    {
        "text": "p5.js lerp()",
        "link": "https://p5js.org/reference/p5.Vector/lerp/"
    },
    {
        "text": "p5.js limit()",
        "link": "https://p5js.org/reference/p5.Vector/limit/"
    },
    {
        "text": "p5.js mag()",
        "link": "https://p5js.org/reference/p5.Vector/mag/"
    },
    {
        "text": "p5.js magSq()",
        "link": "https://p5js.org/reference/p5.Vector/magSq/"
    },
    {
        "text": "p5.js mult()",
        "link": "https://p5js.org/reference/p5.Vector/mult/"
    },
    {
        "text": "p5.js normalize()",
        "link": "https://p5js.org/reference/p5.Vector/normalize/"
    },
    {
        "text": "p5.js random2D()",
        "link": "https://p5js.org/reference/p5.Vector/random2D/"
    },
    {
        "text": "p5.js random3D()",
        "link": "https://p5js.org/reference/p5.Vector/random3D/"
    },
    {
        "text": "p5.js reflect()",
        "link": "https://p5js.org/reference/p5.Vector/reflect/"
    },
    {
        "text": "p5.js rem()",
        "link": "https://p5js.org/reference/p5.Vector/rem/"
    },
    {
        "text": "p5.js rotate()",
        "link": "https://p5js.org/reference/p5.Vector/rotate/"
    },
    {
        "text": "p5.js set()",
        "link": "https://p5js.org/reference/p5.Vector/set/"
    },
    {
        "text": "p5.js setHeading()",
        "link": "https://p5js.org/reference/p5.Vector/setHeading/"
    },
    {
        "text": "p5.js setMag()",
        "link": "https://p5js.org/reference/p5.Vector/setMag/"
    },
    {
        "text": "p5.js slerp()",
        "link": "https://p5js.org/reference/p5.Vector/slerp/"
    },
    {
        "text": "p5.js sub()",
        "link": "https://p5js.org/reference/p5.Vector/sub/"
    },
    {
        "text": "p5.js toString()",
        "link": "https://p5js.org/reference/p5.Vector/toString/"
    },
    {
        "text": "p5.js x",
        "link": "https://p5js.org/reference/p5.Vector/x/"
    },
    {
        "text": "p5.js y",
        "link": "https://p5js.org/reference/p5.Vector/y/"
    },
    {
        "text": "p5.js z",
        "link": "https://p5js.org/reference/p5.Vector/z/"
    },
    {
        "text": "p5.js httpDo()",
        "link": "https://p5js.org/reference/p5/httpDo/"
    },
    {
        "text": "p5.js httpGet()",
        "link": "https://p5js.org/reference/p5/httpGet/"
    },
    {
        "text": "p5.js httpPost()",
        "link": "https://p5js.org/reference/p5/httpPost/"
    },
    {
        "text": "p5.js loadBytes()",
        "link": "https://p5js.org/reference/p5/loadBytes/"
    },
    {
        "text": "p5.js loadJSON()",
        "link": "https://p5js.org/reference/p5/loadJSON/"
    },
    {
        "text": "p5.js loadStrings()",
        "link": "https://p5js.org/reference/p5/loadStrings/"
    },
    {
        "text": "p5.js loadTable()",
        "link": "https://p5js.org/reference/p5/loadTable/"
    },
    {
        "text": "p5.js loadXML()",
        "link": "https://p5js.org/reference/p5/loadXML/"
    },
    {
        "text": "p5.js createWriter()",
        "link": "https://p5js.org/reference/p5/createWriter/"
    },
    {
        "text": "p5.js p5.PrintWriter",
        "link": "https://p5js.org/reference/p5/p5.PrintWriter/"
    },
    {
        "text": "p5.js save()",
        "link": "https://p5js.org/reference/p5/save/"
    },
    {
        "text": "p5.js saveJSON()",
        "link": "https://p5js.org/reference/p5/saveJSON/"
    },
    {
        "text": "p5.js saveStrings()",
        "link": "https://p5js.org/reference/p5/saveStrings/"
    },
    {
        "text": "p5.js saveTable()",
        "link": "https://p5js.org/reference/p5/saveTable/"
    },
    {
        "text": "p5.js day()",
        "link": "https://p5js.org/reference/p5/day/"
    },
    {
        "text": "p5.js hour()",
        "link": "https://p5js.org/reference/p5/hour/"
    },
    {
        "text": "p5.js millis()",
        "link": "https://p5js.org/reference/p5/millis/"
    },
    {
        "text": "p5.js minute()",
        "link": "https://p5js.org/reference/p5/minute/"
    },
    {
        "text": "p5.js month()",
        "link": "https://p5js.org/reference/p5/month/"
    },
    {
        "text": "p5.js second()",
        "link": "https://p5js.org/reference/p5/second/"
    },
    {
        "text": "p5.js year()",
        "link": "https://p5js.org/reference/p5/year/"
    },
    {
        "text": "p5.js addColumn()",
        "link": "https://p5js.org/reference/p5.Table/addColumn/"
    },
    {
        "text": "p5.js addRow()",
        "link": "https://p5js.org/reference/p5.Table/addRow/"
    },
    {
        "text": "p5.js clearRows()",
        "link": "https://p5js.org/reference/p5.Table/clearRows/"
    },
    {
        "text": "p5.js columns",
        "link": "https://p5js.org/reference/p5.Table/columns/"
    },
    {
        "text": "p5.js findRow()",
        "link": "https://p5js.org/reference/p5.Table/findRow/"
    },
    {
        "text": "p5.js findRows()",
        "link": "https://p5js.org/reference/p5.Table/findRows/"
    },
    {
        "text": "p5.js get()",
        "link": "https://p5js.org/reference/p5.Table/get/"
    },
    {
        "text": "p5.js getArray()",
        "link": "https://p5js.org/reference/p5.Table/getArray/"
    },
    {
        "text": "p5.js getColumn()",
        "link": "https://p5js.org/reference/p5.Table/getColumn/"
    },
    {
        "text": "p5.js getColumnCount()",
        "link": "https://p5js.org/reference/p5.Table/getColumnCount/"
    },
    {
        "text": "p5.js getNum()",
        "link": "https://p5js.org/reference/p5.Table/getNum/"
    },
    {
        "text": "p5.js getObject()",
        "link": "https://p5js.org/reference/p5.Table/getObject/"
    },
    {
        "text": "p5.js getRow()",
        "link": "https://p5js.org/reference/p5.Table/getRow/"
    },
    {
        "text": "p5.js getRowCount()",
        "link": "https://p5js.org/reference/p5.Table/getRowCount/"
    },
    {
        "text": "p5.js getRows()",
        "link": "https://p5js.org/reference/p5.Table/getRows/"
    },
    {
        "text": "p5.js getString()",
        "link": "https://p5js.org/reference/p5.Table/getString/"
    },
    {
        "text": "p5.js matchRow()",
        "link": "https://p5js.org/reference/p5.Table/matchRow/"
    },
    {
        "text": "p5.js matchRows()",
        "link": "https://p5js.org/reference/p5.Table/matchRows/"
    },
    {
        "text": "p5.js removeColumn()",
        "link": "https://p5js.org/reference/p5.Table/removeColumn/"
    },
    {
        "text": "p5.js removeRow()",
        "link": "https://p5js.org/reference/p5.Table/removeRow/"
    },
    {
        "text": "p5.js removeTokens()",
        "link": "https://p5js.org/reference/p5.Table/removeTokens/"
    },
    {
        "text": "p5.js rows",
        "link": "https://p5js.org/reference/p5.Table/rows/"
    },
    {
        "text": "p5.js set()",
        "link": "https://p5js.org/reference/p5.Table/set/"
    },
    {
        "text": "p5.js setNum()",
        "link": "https://p5js.org/reference/p5.Table/setNum/"
    },
    {
        "text": "p5.js setString()",
        "link": "https://p5js.org/reference/p5.Table/setString/"
    },
    {
        "text": "p5.js trim()",
        "link": "https://p5js.org/reference/p5.Table/trim/"
    },
    {
        "text": "p5.js get()",
        "link": "https://p5js.org/reference/p5.TableRow/get/"
    },
    {
        "text": "p5.js getNum()",
        "link": "https://p5js.org/reference/p5.TableRow/getNum/"
    },
    {
        "text": "p5.js getString()",
        "link": "https://p5js.org/reference/p5.TableRow/getString/"
    },
    {
        "text": "p5.js set()",
        "link": "https://p5js.org/reference/p5.TableRow/set/"
    },
    {
        "text": "p5.js setNum()",
        "link": "https://p5js.org/reference/p5.TableRow/setNum/"
    },
    {
        "text": "p5.js setString()",
        "link": "https://p5js.org/reference/p5.TableRow/setString/"
    },
    {
        "text": "p5.js addChild()",
        "link": "https://p5js.org/reference/p5.XML/addChild/"
    },
    {
        "text": "p5.js getAttributeCount()",
        "link": "https://p5js.org/reference/p5.XML/getAttributeCount/"
    },
    {
        "text": "p5.js getChild()",
        "link": "https://p5js.org/reference/p5.XML/getChild/"
    },
    {
        "text": "p5.js getChildren()",
        "link": "https://p5js.org/reference/p5.XML/getChildren/"
    },
    {
        "text": "p5.js getContent()",
        "link": "https://p5js.org/reference/p5.XML/getContent/"
    },
    {
        "text": "p5.js getName()",
        "link": "https://p5js.org/reference/p5.XML/getName/"
    },
    {
        "text": "p5.js getNum()",
        "link": "https://p5js.org/reference/p5.XML/getNum/"
    },
    {
        "text": "p5.js getParent()",
        "link": "https://p5js.org/reference/p5.XML/getParent/"
    },
    {
        "text": "p5.js getString()",
        "link": "https://p5js.org/reference/p5.XML/getString/"
    },
    {
        "text": "p5.js hasAttribute()",
        "link": "https://p5js.org/reference/p5.XML/hasAttribute/"
    },
    {
        "text": "p5.js hasChildren()",
        "link": "https://p5js.org/reference/p5.XML/hasChildren/"
    },
    {
        "text": "p5.js listAttributes()",
        "link": "https://p5js.org/reference/p5.XML/listAttributes/"
    },
    {
        "text": "p5.js listChildren()",
        "link": "https://p5js.org/reference/p5.XML/listChildren/"
    },
    {
        "text": "p5.js removeChild()",
        "link": "https://p5js.org/reference/p5.XML/removeChild/"
    },
    {
        "text": "p5.js serialize()",
        "link": "https://p5js.org/reference/p5.XML/serialize/"
    },
    {
        "text": "p5.js setAttribute()",
        "link": "https://p5js.org/reference/p5.XML/setAttribute/"
    },
    {
        "text": "p5.js setContent()",
        "link": "https://p5js.org/reference/p5.XML/setContent/"
    },
    {
        "text": "p5.js setName()",
        "link": "https://p5js.org/reference/p5.XML/setName/"
    },
    {
        "text": "p5.js accelerationX",
        "link": "https://p5js.org/reference/p5/accelerationX/"
    },
    {
        "text": "p5.js accelerationY",
        "link": "https://p5js.org/reference/p5/accelerationY/"
    },
    {
        "text": "p5.js accelerationZ",
        "link": "https://p5js.org/reference/p5/accelerationZ/"
    },
    {
        "text": "p5.js deviceMoved()",
        "link": "https://p5js.org/reference/p5/deviceMoved/"
    },
    {
        "text": "p5.js deviceOrientation",
        "link": "https://p5js.org/reference/p5/deviceOrientation/"
    },
    {
        "text": "p5.js deviceShaken()",
        "link": "https://p5js.org/reference/p5/deviceShaken/"
    },
    {
        "text": "p5.js deviceTurned()",
        "link": "https://p5js.org/reference/p5/deviceTurned/"
    },
    {
        "text": "p5.js pAccelerationX",
        "link": "https://p5js.org/reference/p5/pAccelerationX/"
    },
    {
        "text": "p5.js pAccelerationY",
        "link": "https://p5js.org/reference/p5/pAccelerationY/"
    },
    {
        "text": "p5.js pAccelerationZ",
        "link": "https://p5js.org/reference/p5/pAccelerationZ/"
    },
    {
        "text": "p5.js pRotationX",
        "link": "https://p5js.org/reference/p5/pRotationX/"
    },
    {
        "text": "p5.js pRotationY",
        "link": "https://p5js.org/reference/p5/pRotationY/"
    },
    {
        "text": "p5.js pRotationZ",
        "link": "https://p5js.org/reference/p5/pRotationZ/"
    },
    {
        "text": "p5.js rotationX",
        "link": "https://p5js.org/reference/p5/rotationX/"
    },
    {
        "text": "p5.js rotationY",
        "link": "https://p5js.org/reference/p5/rotationY/"
    },
    {
        "text": "p5.js rotationZ",
        "link": "https://p5js.org/reference/p5/rotationZ/"
    },
    {
        "text": "p5.js setMoveThreshold()",
        "link": "https://p5js.org/reference/p5/setMoveThreshold/"
    },
    {
        "text": "p5.js setShakeThreshold()",
        "link": "https://p5js.org/reference/p5/setShakeThreshold/"
    },
    {
        "text": "p5.js turnAxis",
        "link": "https://p5js.org/reference/p5/turnAxis/"
    },
    {
        "text": "p5.js key",
        "link": "https://p5js.org/reference/p5/key/"
    },
    {
        "text": "p5.js keyCode",
        "link": "https://p5js.org/reference/p5/keyCode/"
    },
    {
        "text": "p5.js keyIsDown()",
        "link": "https://p5js.org/reference/p5/keyIsDown/"
    },
    {
        "text": "p5.js keyIsPressed",
        "link": "https://p5js.org/reference/p5/keyIsPressed/"
    },
    {
        "text": "p5.js keyPressed()",
        "link": "https://p5js.org/reference/p5/keyPressed/"
    },
    {
        "text": "p5.js keyReleased()",
        "link": "https://p5js.org/reference/p5/keyReleased/"
    },
    {
        "text": "p5.js keyTyped()",
        "link": "https://p5js.org/reference/p5/keyTyped/"
    },
    {
        "text": "p5.js doubleClicked()",
        "link": "https://p5js.org/reference/p5/doubleClicked/"
    },
    {
        "text": "p5.js exitPointerLock()",
        "link": "https://p5js.org/reference/p5/exitPointerLock/"
    },
    {
        "text": "p5.js mouseButton",
        "link": "https://p5js.org/reference/p5/mouseButton/"
    },
    {
        "text": "p5.js mouseClicked()",
        "link": "https://p5js.org/reference/p5/mouseClicked/"
    },
    {
        "text": "p5.js mouseDragged()",
        "link": "https://p5js.org/reference/p5/mouseDragged/"
    },
    {
        "text": "p5.js mouseIsPressed",
        "link": "https://p5js.org/reference/p5/mouseIsPressed/"
    },
    {
        "text": "p5.js mouseMoved()",
        "link": "https://p5js.org/reference/p5/mouseMoved/"
    },
    {
        "text": "p5.js mousePressed()",
        "link": "https://p5js.org/reference/p5/mousePressed/"
    },
    {
        "text": "p5.js mouseReleased()",
        "link": "https://p5js.org/reference/p5/mouseReleased/"
    },
    {
        "text": "p5.js mouseWheel()",
        "link": "https://p5js.org/reference/p5/mouseWheel/"
    },
    {
        "text": "p5.js mouseX",
        "link": "https://p5js.org/reference/p5/mouseX/"
    },
    {
        "text": "p5.js mouseY",
        "link": "https://p5js.org/reference/p5/mouseY/"
    },
    {
        "text": "p5.js movedX",
        "link": "https://p5js.org/reference/p5/movedX/"
    },
    {
        "text": "p5.js movedY",
        "link": "https://p5js.org/reference/p5/movedY/"
    },
    {
        "text": "p5.js pmouseX",
        "link": "https://p5js.org/reference/p5/pmouseX/"
    },
    {
        "text": "p5.js pmouseY",
        "link": "https://p5js.org/reference/p5/pmouseY/"
    },
    {
        "text": "p5.js pwinMouseX",
        "link": "https://p5js.org/reference/p5/pwinMouseX/"
    },
    {
        "text": "p5.js pwinMouseY",
        "link": "https://p5js.org/reference/p5/pwinMouseY/"
    },
    {
        "text": "p5.js requestPointerLock()",
        "link": "https://p5js.org/reference/p5/requestPointerLock/"
    },
    {
        "text": "p5.js winMouseX",
        "link": "https://p5js.org/reference/p5/winMouseX/"
    },
    {
        "text": "p5.js winMouseY",
        "link": "https://p5js.org/reference/p5/winMouseY/"
    },
    {
        "text": "p5.js touchEnded()",
        "link": "https://p5js.org/reference/p5/touchEnded/"
    },
    {
        "text": "p5.js touchMoved()",
        "link": "https://p5js.org/reference/p5/touchMoved/"
    },
    {
        "text": "p5.js touchStarted()",
        "link": "https://p5js.org/reference/p5/touchStarted/"
    },
    {
        "text": "p5.js touches",
        "link": "https://p5js.org/reference/p5/touches/"
    },
    {
        "text": "p5.js changed()",
        "link": "https://p5js.org/reference/p5/changed/"
    },
    {
        "text": "p5.js createA()",
        "link": "https://p5js.org/reference/p5/createA/"
    },
    {
        "text": "p5.js createAudio()",
        "link": "https://p5js.org/reference/p5/createAudio/"
    },
    {
        "text": "p5.js createButton()",
        "link": "https://p5js.org/reference/p5/createButton/"
    },
    {
        "text": "p5.js createCapture()",
        "link": "https://p5js.org/reference/p5/createCapture/"
    },
    {
        "text": "p5.js createCheckbox()",
        "link": "https://p5js.org/reference/p5/createCheckbox/"
    },
    {
        "text": "p5.js createColorPicker()",
        "link": "https://p5js.org/reference/p5/createColorPicker/"
    },
    {
        "text": "p5.js createDiv()",
        "link": "https://p5js.org/reference/p5/createDiv/"
    },
    {
        "text": "p5.js createElement()",
        "link": "https://p5js.org/reference/p5/createElement/"
    },
    {
        "text": "p5.js createFileInput()",
        "link": "https://p5js.org/reference/p5/createFileInput/"
    },
    {
        "text": "p5.js createImg()",
        "link": "https://p5js.org/reference/p5/createImg/"
    },
    {
        "text": "p5.js createInput()",
        "link": "https://p5js.org/reference/p5/createInput/"
    },
    {
        "text": "p5.js createP()",
        "link": "https://p5js.org/reference/p5/createP/"
    },
    {
        "text": "p5.js createRadio()",
        "link": "https://p5js.org/reference/p5/createRadio/"
    },
    {
        "text": "p5.js createSelect()",
        "link": "https://p5js.org/reference/p5/createSelect/"
    },
    {
        "text": "p5.js createSlider()",
        "link": "https://p5js.org/reference/p5/createSlider/"
    },
    {
        "text": "p5.js createSpan()",
        "link": "https://p5js.org/reference/p5/createSpan/"
    },
    {
        "text": "p5.js createVideo()",
        "link": "https://p5js.org/reference/p5/createVideo/"
    },
    {
        "text": "p5.js input()",
        "link": "https://p5js.org/reference/p5/input/"
    },
    {
        "text": "p5.js removeElements()",
        "link": "https://p5js.org/reference/p5/removeElements/"
    },
    {
        "text": "p5.js select()",
        "link": "https://p5js.org/reference/p5/select/"
    },
    {
        "text": "p5.js selectAll()",
        "link": "https://p5js.org/reference/p5/selectAll/"
    },
    {
        "text": "p5.js addClass()",
        "link": "https://p5js.org/reference/p5.Element/addClass/"
    },
    {
        "text": "p5.js attribute()",
        "link": "https://p5js.org/reference/p5.Element/attribute/"
    },
    {
        "text": "p5.js center()",
        "link": "https://p5js.org/reference/p5.Element/center/"
    },
    {
        "text": "p5.js child()",
        "link": "https://p5js.org/reference/p5.Element/child/"
    },
    {
        "text": "p5.js class()",
        "link": "https://p5js.org/reference/p5.Element/class/"
    },
    {
        "text": "p5.js doubleClicked()",
        "link": "https://p5js.org/reference/p5.Element/doubleClicked/"
    },
    {
        "text": "p5.js dragLeave()",
        "link": "https://p5js.org/reference/p5.Element/dragLeave/"
    },
    {
        "text": "p5.js dragOver()",
        "link": "https://p5js.org/reference/p5.Element/dragOver/"
    },
    {
        "text": "p5.js draggable()",
        "link": "https://p5js.org/reference/p5.Element/draggable/"
    },
    {
        "text": "p5.js drop()",
        "link": "https://p5js.org/reference/p5.Element/drop/"
    },
    {
        "text": "p5.js elt",
        "link": "https://p5js.org/reference/p5.Element/elt/"
    },
    {
        "text": "p5.js hasClass()",
        "link": "https://p5js.org/reference/p5.Element/hasClass/"
    },
    {
        "text": "p5.js height",
        "link": "https://p5js.org/reference/p5.Element/height/"
    },
    {
        "text": "p5.js hide()",
        "link": "https://p5js.org/reference/p5.Element/hide/"
    },
    {
        "text": "p5.js html()",
        "link": "https://p5js.org/reference/p5.Element/html/"
    },
    {
        "text": "p5.js id()",
        "link": "https://p5js.org/reference/p5.Element/id/"
    },
    {
        "text": "p5.js mouseClicked()",
        "link": "https://p5js.org/reference/p5.Element/mouseClicked/"
    },
    {
        "text": "p5.js mouseMoved()",
        "link": "https://p5js.org/reference/p5.Element/mouseMoved/"
    },
    {
        "text": "p5.js mouseOut()",
        "link": "https://p5js.org/reference/p5.Element/mouseOut/"
    },
    {
        "text": "p5.js mouseOver()",
        "link": "https://p5js.org/reference/p5.Element/mouseOver/"
    },
    {
        "text": "p5.js mousePressed()",
        "link": "https://p5js.org/reference/p5.Element/mousePressed/"
    },
    {
        "text": "p5.js mouseReleased()",
        "link": "https://p5js.org/reference/p5.Element/mouseReleased/"
    },
    {
        "text": "p5.js mouseWheel()",
        "link": "https://p5js.org/reference/p5.Element/mouseWheel/"
    },
    {
        "text": "p5.js parent()",
        "link": "https://p5js.org/reference/p5.Element/parent/"
    },
    {
        "text": "p5.js position()",
        "link": "https://p5js.org/reference/p5.Element/position/"
    },
    {
        "text": "p5.js remove()",
        "link": "https://p5js.org/reference/p5.Element/remove/"
    },
    {
        "text": "p5.js removeAttribute()",
        "link": "https://p5js.org/reference/p5.Element/removeAttribute/"
    },
    {
        "text": "p5.js removeClass()",
        "link": "https://p5js.org/reference/p5.Element/removeClass/"
    },
    {
        "text": "p5.js show()",
        "link": "https://p5js.org/reference/p5.Element/show/"
    },
    {
        "text": "p5.js size()",
        "link": "https://p5js.org/reference/p5.Element/size/"
    },
    {
        "text": "p5.js style()",
        "link": "https://p5js.org/reference/p5.Element/style/"
    },
    {
        "text": "p5.js toggleClass()",
        "link": "https://p5js.org/reference/p5.Element/toggleClass/"
    },
    {
        "text": "p5.js touchEnded()",
        "link": "https://p5js.org/reference/p5.Element/touchEnded/"
    },
    {
        "text": "p5.js touchMoved()",
        "link": "https://p5js.org/reference/p5.Element/touchMoved/"
    },
    {
        "text": "p5.js touchStarted()",
        "link": "https://p5js.org/reference/p5.Element/touchStarted/"
    },
    {
        "text": "p5.js value()",
        "link": "https://p5js.org/reference/p5.Element/value/"
    },
    {
        "text": "p5.js width",
        "link": "https://p5js.org/reference/p5.Element/width/"
    },
    {
        "text": "p5.js data",
        "link": "https://p5js.org/reference/p5.File/data/"
    },
    {
        "text": "p5.js file",
        "link": "https://p5js.org/reference/p5.File/file/"
    },
    {
        "text": "p5.js name",
        "link": "https://p5js.org/reference/p5.File/name/"
    },
    {
        "text": "p5.js size",
        "link": "https://p5js.org/reference/p5.File/size/"
    },
    {
        "text": "p5.js subtype",
        "link": "https://p5js.org/reference/p5.File/subtype/"
    },
    {
        "text": "p5.js type",
        "link": "https://p5js.org/reference/p5.File/type/"
    },
    {
        "text": "p5.js addCue()",
        "link": "https://p5js.org/reference/p5.MediaElement/addCue/"
    },
    {
        "text": "p5.js autoplay()",
        "link": "https://p5js.org/reference/p5.MediaElement/autoplay/"
    },
    {
        "text": "p5.js clearCues()",
        "link": "https://p5js.org/reference/p5.MediaElement/clearCues/"
    },
    {
        "text": "p5.js connect()",
        "link": "https://p5js.org/reference/p5.MediaElement/connect/"
    },
    {
        "text": "p5.js disconnect()",
        "link": "https://p5js.org/reference/p5.MediaElement/disconnect/"
    },
    {
        "text": "p5.js duration()",
        "link": "https://p5js.org/reference/p5.MediaElement/duration/"
    },
    {
        "text": "p5.js hideControls()",
        "link": "https://p5js.org/reference/p5.MediaElement/hideControls/"
    },
    {
        "text": "p5.js loop()",
        "link": "https://p5js.org/reference/p5.MediaElement/loop/"
    },
    {
        "text": "p5.js noLoop()",
        "link": "https://p5js.org/reference/p5.MediaElement/noLoop/"
    },
    {
        "text": "p5.js onended()",
        "link": "https://p5js.org/reference/p5.MediaElement/onended/"
    },
    {
        "text": "p5.js pause()",
        "link": "https://p5js.org/reference/p5.MediaElement/pause/"
    },
    {
        "text": "p5.js play()",
        "link": "https://p5js.org/reference/p5.MediaElement/play/"
    },
    {
        "text": "p5.js removeCue()",
        "link": "https://p5js.org/reference/p5.MediaElement/removeCue/"
    },
    {
        "text": "p5.js showControls()",
        "link": "https://p5js.org/reference/p5.MediaElement/showControls/"
    },
    {
        "text": "p5.js speed()",
        "link": "https://p5js.org/reference/p5.MediaElement/speed/"
    },
    {
        "text": "p5.js src",
        "link": "https://p5js.org/reference/p5.MediaElement/src/"
    },
    {
        "text": "p5.js stop()",
        "link": "https://p5js.org/reference/p5.MediaElement/stop/"
    },
    {
        "text": "p5.js time()",
        "link": "https://p5js.org/reference/p5.MediaElement/time/"
    },
    {
        "text": "p5.js volume()",
        "link": "https://p5js.org/reference/p5.MediaElement/volume/"
    },
    {
        "text": "p5.js append()",
        "link": "https://p5js.org/reference/p5/append/"
    },
    {
        "text": "p5.js arrayCopy()",
        "link": "https://p5js.org/reference/p5/arrayCopy/"
    },
    {
        "text": "p5.js concat()",
        "link": "https://p5js.org/reference/p5/concat/"
    },
    {
        "text": "p5.js reverse()",
        "link": "https://p5js.org/reference/p5/reverse/"
    },
    {
        "text": "p5.js shorten()",
        "link": "https://p5js.org/reference/p5/shorten/"
    },
    {
        "text": "p5.js shuffle()",
        "link": "https://p5js.org/reference/p5/shuffle/"
    },
    {
        "text": "p5.js sort()",
        "link": "https://p5js.org/reference/p5/sort/"
    },
    {
        "text": "p5.js splice()",
        "link": "https://p5js.org/reference/p5/splice/"
    },
    {
        "text": "p5.js subset()",
        "link": "https://p5js.org/reference/p5/subset/"
    },
    {
        "text": "p5.js boolean()",
        "link": "https://p5js.org/reference/p5/boolean/"
    },
    {
        "text": "p5.js byte()",
        "link": "https://p5js.org/reference/p5/byte/"
    },
    {
        "text": "p5.js char()",
        "link": "https://p5js.org/reference/p5/char/"
    },
    {
        "text": "p5.js float()",
        "link": "https://p5js.org/reference/p5/float/"
    },
    {
        "text": "p5.js hex()",
        "link": "https://p5js.org/reference/p5/hex/"
    },
    {
        "text": "p5.js int()",
        "link": "https://p5js.org/reference/p5/int/"
    },
    {
        "text": "p5.js str()",
        "link": "https://p5js.org/reference/p5/str/"
    },
    {
        "text": "p5.js unchar()",
        "link": "https://p5js.org/reference/p5/unchar/"
    },
    {
        "text": "p5.js unhex()",
        "link": "https://p5js.org/reference/p5/unhex/"
    },
    {
        "text": "p5.js createNumberDict()",
        "link": "https://p5js.org/reference/p5/createNumberDict/"
    },
    {
        "text": "p5.js createStringDict()",
        "link": "https://p5js.org/reference/p5/createStringDict/"
    },
    {
        "text": "p5.js p5.StringDict",
        "link": "https://p5js.org/reference/p5/p5.StringDict/"
    },
    {
        "text": "p5.js clearStorage()",
        "link": "https://p5js.org/reference/p5/clearStorage/"
    },
    {
        "text": "p5.js getItem()",
        "link": "https://p5js.org/reference/p5/getItem/"
    },
    {
        "text": "p5.js removeItem()",
        "link": "https://p5js.org/reference/p5/removeItem/"
    },
    {
        "text": "p5.js storeItem()",
        "link": "https://p5js.org/reference/p5/storeItem/"
    },
    {
        "text": "p5.js join()",
        "link": "https://p5js.org/reference/p5/join/"
    },
    {
        "text": "p5.js match()",
        "link": "https://p5js.org/reference/p5/match/"
    },
    {
        "text": "p5.js matchAll()",
        "link": "https://p5js.org/reference/p5/matchAll/"
    },
    {
        "text": "p5.js nf()",
        "link": "https://p5js.org/reference/p5/nf/"
    },
    {
        "text": "p5.js nfc()",
        "link": "https://p5js.org/reference/p5/nfc/"
    },
    {
        "text": "p5.js nfp()",
        "link": "https://p5js.org/reference/p5/nfp/"
    },
    {
        "text": "p5.js nfs()",
        "link": "https://p5js.org/reference/p5/nfs/"
    },
    {
        "text": "p5.js split()",
        "link": "https://p5js.org/reference/p5/split/"
    },
    {
        "text": "p5.js splitTokens()",
        "link": "https://p5js.org/reference/p5/splitTokens/"
    },
    {
        "text": "p5.js trim()",
        "link": "https://p5js.org/reference/p5/trim/"
    },
    {
        "text": "p5.js add()",
        "link": "https://p5js.org/reference/p5.NumberDict/add/"
    },
    {
        "text": "p5.js div()",
        "link": "https://p5js.org/reference/p5.NumberDict/div/"
    },
    {
        "text": "p5.js maxKey()",
        "link": "https://p5js.org/reference/p5.NumberDict/maxKey/"
    },
    {
        "text": "p5.js maxValue()",
        "link": "https://p5js.org/reference/p5.NumberDict/maxValue/"
    },
    {
        "text": "p5.js minKey()",
        "link": "https://p5js.org/reference/p5.NumberDict/minKey/"
    },
    {
        "text": "p5.js minValue()",
        "link": "https://p5js.org/reference/p5.NumberDict/minValue/"
    },
    {
        "text": "p5.js mult()",
        "link": "https://p5js.org/reference/p5.NumberDict/mult/"
    },
    {
        "text": "p5.js sub()",
        "link": "https://p5js.org/reference/p5.NumberDict/sub/"
    },
    {
        "text": "p5.js clear()",
        "link": "https://p5js.org/reference/p5.TypedDict/clear/"
    },
    {
        "text": "p5.js create()",
        "link": "https://p5js.org/reference/p5.TypedDict/create/"
    },
    {
        "text": "p5.js get()",
        "link": "https://p5js.org/reference/p5.TypedDict/get/"
    },
    {
        "text": "p5.js hasKey()",
        "link": "https://p5js.org/reference/p5.TypedDict/hasKey/"
    },
    {
        "text": "p5.js print()",
        "link": "https://p5js.org/reference/p5.TypedDict/print/"
    },
    {
        "text": "p5.js remove()",
        "link": "https://p5js.org/reference/p5.TypedDict/remove/"
    },
    {
        "text": "p5.js saveJSON()",
        "link": "https://p5js.org/reference/p5.TypedDict/saveJSON/"
    },
    {
        "text": "p5.js saveTable()",
        "link": "https://p5js.org/reference/p5.TypedDict/saveTable/"
    },
    {
        "text": "p5.js set()",
        "link": "https://p5js.org/reference/p5.TypedDict/set/"
    },
    {
        "text": "p5.js size()",
        "link": "https://p5js.org/reference/p5.TypedDict/size/"
    },
    {
        "text": "p5.js disableFriendlyErrors",
        "link": "https://p5js.org/reference/p5/disableFriendlyErrors/"
    },
    {
        "text": "p5.js draw()",
        "link": "https://p5js.org/reference/p5/draw/"
    },
    {
        "text": "p5.js isLooping()",
        "link": "https://p5js.org/reference/p5/isLooping/"
    },
    {
        "text": "p5.js loop()",
        "link": "https://p5js.org/reference/p5/loop/"
    },
    {
        "text": "p5.js noLoop()",
        "link": "https://p5js.org/reference/p5/noLoop/"
    },
    {
        "text": "p5.js pop()",
        "link": "https://p5js.org/reference/p5/pop/"
    },
    {
        "text": "p5.js preload()",
        "link": "https://p5js.org/reference/p5/preload/"
    },
    {
        "text": "p5.js push()",
        "link": "https://p5js.org/reference/p5/push/"
    },
    {
        "text": "p5.js redraw()",
        "link": "https://p5js.org/reference/p5/redraw/"
    },
    {
        "text": "p5.js remove()",
        "link": "https://p5js.org/reference/p5/remove/"
    },
    {
        "text": "p5.js setup()",
        "link": "https://p5js.org/reference/p5/setup/"
    },
    {
        "text": "p5.js AUTO",
        "link": "https://p5js.org/reference/p5/AUTO/"
    },
    {
        "text": "p5.js DEGREES",
        "link": "https://p5js.org/reference/p5/DEGREES/"
    },
    {
        "text": "p5.js HALF_PI",
        "link": "https://p5js.org/reference/p5/HALF_PI/"
    },
    {
        "text": "p5.js HSB",
        "link": "https://p5js.org/reference/p5/HSB/"
    },
    {
        "text": "p5.js P2D",
        "link": "https://p5js.org/reference/p5/P2D/"
    },
    {
        "text": "p5.js PI",
        "link": "https://p5js.org/reference/p5/PI/"
    },
    {
        "text": "p5.js QUARTER_PI",
        "link": "https://p5js.org/reference/p5/QUARTER_PI/"
    },
    {
        "text": "p5.js RADIANS",
        "link": "https://p5js.org/reference/p5/RADIANS/"
    },
    {
        "text": "p5.js TAU",
        "link": "https://p5js.org/reference/p5/TAU/"
    },
    {
        "text": "p5.js TWO_PI",
        "link": "https://p5js.org/reference/p5/TWO_PI/"
    },
    {
        "text": "p5.js VERSION",
        "link": "https://p5js.org/reference/p5/VERSION/"
    },
    {
        "text": "p5.js WEBGL",
        "link": "https://p5js.org/reference/p5/WEBGL/"
    },
    {
        "text": "p5.js WEBGL2",
        "link": "https://p5js.org/reference/p5/WEBGL2/"
    },
    {
        "text": "p5.js Array",
        "link": "https://p5js.org/reference/p5/Array/"
    },
    {
        "text": "p5.js Number",
        "link": "https://p5js.org/reference/p5/Number/"
    },
    {
        "text": "p5.js Object",
        "link": "https://p5js.org/reference/p5/Object/"
    },
    {
        "text": "p5.js String",
        "link": "https://p5js.org/reference/p5/String/"
    },
    {
        "text": "p5.js class",
        "link": "https://p5js.org/reference/p5/class/"
    },
    {
        "text": "p5.js console",
        "link": "https://p5js.org/reference/p5/console/"
    },
    {
        "text": "p5.js for",
        "link": "https://p5js.org/reference/p5/for/"
    },
    {
        "text": "p5.js function",
        "link": "https://p5js.org/reference/p5/function/"
    },
    {
        "text": "p5.js if",
        "link": "https://p5js.org/reference/p5/if/"
    },
    {
        "text": "p5.js let",
        "link": "https://p5js.org/reference/p5/let/"
    },
    {
        "text": "p5.js while",
        "link": "https://p5js.org/reference/p5/while/"
    }
]