[
    {
        "text": "arc()",
        "link": "https://p5js.org/reference/p5/arc/"
    },
    {
        "text": "circle()",
        "link": "https://p5js.org/reference/p5/circle/"
    },
    {
        "text": "ellipse()",
        "link": "https://p5js.org/reference/p5/ellipse/"
    },
    {
        "text": "line()",
        "link": "https://p5js.org/reference/p5/line/"
    },
    {
        "text": "point()",
        "link": "https://p5js.org/reference/p5/point/"
    },
    {
        "text": "quad()",
        "link": "https://p5js.org/reference/p5/quad/"
    },
    {
        "text": "rect()",
        "link": "https://p5js.org/reference/p5/rect/"
    },
    {
        "text": "square()",
        "link": "https://p5js.org/reference/p5/square/"
    },
    {
        "text": "triangle()",
        "link": "https://p5js.org/reference/p5/triangle/"
    },
    {
        "text": "createModel()",
        "link": "https://p5js.org/reference/p5/createModel/"
    },
    {
        "text": "loadModel()",
        "link": "https://p5js.org/reference/p5/loadModel/"
    },
    {
        "text": "model()",
        "link": "https://p5js.org/reference/p5/model/"
    },
    {
        "text": "beginGeometry()",
        "link": "https://p5js.org/reference/p5/beginGeometry/"
    },
    {
        "text": "box()",
        "link": "https://p5js.org/reference/p5/box/"
    },
    {
        "text": "buildGeometry()",
        "link": "https://p5js.org/reference/p5/buildGeometry/"
    },
    {
        "text": "cone()",
        "link": "https://p5js.org/reference/p5/cone/"
    },
    {
        "text": "cylinder()",
        "link": "https://p5js.org/reference/p5/cylinder/"
    },
    {
        "text": "ellipsoid()",
        "link": "https://p5js.org/reference/p5/ellipsoid/"
    },
    {
        "text": "endGeometry()",
        "link": "https://p5js.org/reference/p5/endGeometry/"
    },
    {
        "text": "freeGeometry()",
        "link": "https://p5js.org/reference/p5/freeGeometry/"
    },
    {
        "text": "plane()",
        "link": "https://p5js.org/reference/p5/plane/"
    },
    {
        "text": "sphere()",
        "link": "https://p5js.org/reference/p5/sphere/"
    },
    {
        "text": "torus()",
        "link": "https://p5js.org/reference/p5/torus/"
    },
    {
        "text": "ellipseMode()",
        "link": "https://p5js.org/reference/p5/ellipseMode/"
    },
    {
        "text": "noSmooth()",
        "link": "https://p5js.org/reference/p5/noSmooth/"
    },
    {
        "text": "rectMode()",
        "link": "https://p5js.org/reference/p5/rectMode/"
    },
    {
        "text": "smooth()",
        "link": "https://p5js.org/reference/p5/smooth/"
    },
    {
        "text": "strokeCap()",
        "link": "https://p5js.org/reference/p5/strokeCap/"
    },
    {
        "text": "strokeJoin()",
        "link": "https://p5js.org/reference/p5/strokeJoin/"
    },
    {
        "text": "strokeWeight()",
        "link": "https://p5js.org/reference/p5/strokeWeight/"
    },
    {
        "text": "bezier()",
        "link": "https://p5js.org/reference/p5/bezier/"
    },
    {
        "text": "bezierDetail()",
        "link": "https://p5js.org/reference/p5/bezierDetail/"
    },
    {
        "text": "bezierPoint()",
        "link": "https://p5js.org/reference/p5/bezierPoint/"
    },
    {
        "text": "bezierTangent()",
        "link": "https://p5js.org/reference/p5/bezierTangent/"
    },
    {
        "text": "curve()",
        "link": "https://p5js.org/reference/p5/curve/"
    },
    {
        "text": "curveDetail()",
        "link": "https://p5js.org/reference/p5/curveDetail/"
    },
    {
        "text": "curvePoint()",
        "link": "https://p5js.org/reference/p5/curvePoint/"
    },
    {
        "text": "curveTangent()",
        "link": "https://p5js.org/reference/p5/curveTangent/"
    },
    {
        "text": "curveTightness()",
        "link": "https://p5js.org/reference/p5/curveTightness/"
    },
    {
        "text": "beginContour()",
        "link": "https://p5js.org/reference/p5/beginContour/"
    },
    {
        "text": "beginShape()",
        "link": "https://p5js.org/reference/p5/beginShape/"
    },
    {
        "text": "bezierVertex()",
        "link": "https://p5js.org/reference/p5/bezierVertex/"
    },
    {
        "text": "curveVertex()",
        "link": "https://p5js.org/reference/p5/curveVertex/"
    },
    {
        "text": "endContour()",
        "link": "https://p5js.org/reference/p5/endContour/"
    },
    {
        "text": "endShape()",
        "link": "https://p5js.org/reference/p5/endShape/"
    },
    {
        "text": "normal()",
        "link": "https://p5js.org/reference/p5/normal/"
    },
    {
        "text": "quadraticVertex()",
        "link": "https://p5js.org/reference/p5/quadraticVertex/"
    },
    {
        "text": "vertex()",
        "link": "https://p5js.org/reference/p5/vertex/"
    },
    {
        "text": "calculateBoundingBox()",
        "link": "https://p5js.org/reference/p5.Geometry/calculateBoundingBox/"
    },
    {
        "text": "clearColors()",
        "link": "https://p5js.org/reference/p5.Geometry/clearColors/"
    },
    {
        "text": "computeFaces()",
        "link": "https://p5js.org/reference/p5.Geometry/computeFaces/"
    },
    {
        "text": "computeNormals()",
        "link": "https://p5js.org/reference/p5.Geometry/computeNormals/"
    },
    {
        "text": "faces",
        "link": "https://p5js.org/reference/p5.Geometry/faces/"
    },
    {
        "text": "flipU()",
        "link": "https://p5js.org/reference/p5.Geometry/flipU/"
    },
    {
        "text": "flipV()",
        "link": "https://p5js.org/reference/p5.Geometry/flipV/"
    },
    {
        "text": "normalize()",
        "link": "https://p5js.org/reference/p5.Geometry/normalize/"
    },
    {
        "text": "saveObj()",
        "link": "https://p5js.org/reference/p5.Geometry/saveObj/"
    },
    {
        "text": "saveStl()",
        "link": "https://p5js.org/reference/p5.Geometry/saveStl/"
    },
    {
        "text": "uvs",
        "link": "https://p5js.org/reference/p5.Geometry/uvs/"
    },
    {
        "text": "vertexNormals",
        "link": "https://p5js.org/reference/p5.Geometry/vertexNormals/"
    },
    {
        "text": "vertices",
        "link": "https://p5js.org/reference/p5.Geometry/vertices/"
    },
    {
        "text": "alpha()",
        "link": "https://p5js.org/reference/p5/alpha/"
    },
    {
        "text": "blue()",
        "link": "https://p5js.org/reference/p5/blue/"
    },
    {
        "text": "brightness()",
        "link": "https://p5js.org/reference/p5/brightness/"
    },
    {
        "text": "color()",
        "link": "https://p5js.org/reference/p5/color/"
    },
    {
        "text": "green()",
        "link": "https://p5js.org/reference/p5/green/"
    },
    {
        "text": "hue()",
        "link": "https://p5js.org/reference/p5/hue/"
    },
    {
        "text": "lerpColor()",
        "link": "https://p5js.org/reference/p5/lerpColor/"
    },
    {
        "text": "lightness()",
        "link": "https://p5js.org/reference/p5/lightness/"
    },
    {
        "text": "paletteLerp()",
        "link": "https://p5js.org/reference/p5/paletteLerp/"
    },
    {
        "text": "red()",
        "link": "https://p5js.org/reference/p5/red/"
    },
    {
        "text": "saturation()",
        "link": "https://p5js.org/reference/p5/saturation/"
    },
    {
        "text": "background()",
        "link": "https://p5js.org/reference/p5/background/"
    },
    {
        "text": "beginClip()",
        "link": "https://p5js.org/reference/p5/beginClip/"
    },
    {
        "text": "clear()",
        "link": "https://p5js.org/reference/p5/clear/"
    },
    {
        "text": "clip()",
        "link": "https://p5js.org/reference/p5/clip/"
    },
    {
        "text": "colorMode()",
        "link": "https://p5js.org/reference/p5/colorMode/"
    },
    {
        "text": "endClip()",
        "link": "https://p5js.org/reference/p5/endClip/"
    },
    {
        "text": "erase()",
        "link": "https://p5js.org/reference/p5/erase/"
    },
    {
        "text": "fill()",
        "link": "https://p5js.org/reference/p5/fill/"
    },
    {
        "text": "noErase()",
        "link": "https://p5js.org/reference/p5/noErase/"
    },
    {
        "text": "noFill()",
        "link": "https://p5js.org/reference/p5/noFill/"
    },
    {
        "text": "noStroke()",
        "link": "https://p5js.org/reference/p5/noStroke/"
    },
    {
        "text": "stroke()",
        "link": "https://p5js.org/reference/p5/stroke/"
    },
    {
        "text": "setAlpha()",
        "link": "https://p5js.org/reference/p5.Color/setAlpha/"
    },
    {
        "text": "setBlue()",
        "link": "https://p5js.org/reference/p5.Color/setBlue/"
    },
    {
        "text": "setGreen()",
        "link": "https://p5js.org/reference/p5.Color/setGreen/"
    },
    {
        "text": "setRed()",
        "link": "https://p5js.org/reference/p5.Color/setRed/"
    },
    {
        "text": "toString()",
        "link": "https://p5js.org/reference/p5.Color/toString/"
    },
    {
        "text": "textAlign()",
        "link": "https://p5js.org/reference/p5/textAlign/"
    },
    {
        "text": "textAscent()",
        "link": "https://p5js.org/reference/p5/textAscent/"
    },
    {
        "text": "textDescent()",
        "link": "https://p5js.org/reference/p5/textDescent/"
    },
    {
        "text": "textLeading()",
        "link": "https://p5js.org/reference/p5/textLeading/"
    },
    {
        "text": "textSize()",
        "link": "https://p5js.org/reference/p5/textSize/"
    },
    {
        "text": "textStyle()",
        "link": "https://p5js.org/reference/p5/textStyle/"
    },
    {
        "text": "textWidth()",
        "link": "https://p5js.org/reference/p5/textWidth/"
    },
    {
        "text": "textWrap()",
        "link": "https://p5js.org/reference/p5/textWrap/"
    },
    {
        "text": "loadFont()",
        "link": "https://p5js.org/reference/p5/loadFont/"
    },
    {
        "text": "text()",
        "link": "https://p5js.org/reference/p5/text/"
    },
    {
        "text": "textFont()",
        "link": "https://p5js.org/reference/p5/textFont/"
    },
    {
        "text": "font",
        "link": "https://p5js.org/reference/p5.Font/font/"
    },
    {
        "text": "textBounds()",
        "link": "https://p5js.org/reference/p5.Font/textBounds/"
    },
    {
        "text": "textToPoints()",
        "link": "https://p5js.org/reference/p5.Font/textToPoints/"
    },
    {
        "text": "createImage()",
        "link": "https://p5js.org/reference/p5/createImage/"
    },
    {
        "text": "saveCanvas()",
        "link": "https://p5js.org/reference/p5/saveCanvas/"
    },
    {
        "text": "saveFrames()",
        "link": "https://p5js.org/reference/p5/saveFrames/"
    },
    {
        "text": "image()",
        "link": "https://p5js.org/reference/p5/image/"
    },
    {
        "text": "imageMode()",
        "link": "https://p5js.org/reference/p5/imageMode/"
    },
    {
        "text": "loadImage()",
        "link": "https://p5js.org/reference/p5/loadImage/"
    },
    {
        "text": "noTint()",
        "link": "https://p5js.org/reference/p5/noTint/"
    },
    {
        "text": "saveGif()",
        "link": "https://p5js.org/reference/p5/saveGif/"
    },
    {
        "text": "tint()",
        "link": "https://p5js.org/reference/p5/tint/"
    },
    {
        "text": "blend()",
        "link": "https://p5js.org/reference/p5/blend/"
    },
    {
        "text": "copy()",
        "link": "https://p5js.org/reference/p5/copy/"
    },
    {
        "text": "filter()",
        "link": "https://p5js.org/reference/p5/filter/"
    },
    {
        "text": "get()",
        "link": "https://p5js.org/reference/p5/get/"
    },
    {
        "text": "loadPixels()",
        "link": "https://p5js.org/reference/p5/loadPixels/"
    },
    {
        "text": "pixels",
        "link": "https://p5js.org/reference/p5/pixels/"
    },
    {
        "text": "set()",
        "link": "https://p5js.org/reference/p5/set/"
    },
    {
        "text": "updatePixels()",
        "link": "https://p5js.org/reference/p5/updatePixels/"
    },
    {
        "text": "blend()",
        "link": "https://p5js.org/reference/p5.Image/blend/"
    },
    {
        "text": "copy()",
        "link": "https://p5js.org/reference/p5.Image/copy/"
    },
    {
        "text": "delay()",
        "link": "https://p5js.org/reference/p5.Image/delay/"
    },
    {
        "text": "filter()",
        "link": "https://p5js.org/reference/p5.Image/filter/"
    },
    {
        "text": "get()",
        "link": "https://p5js.org/reference/p5.Image/get/"
    },
    {
        "text": "getCurrentFrame()",
        "link": "https://p5js.org/reference/p5.Image/getCurrentFrame/"
    },
    {
        "text": "height",
        "link": "https://p5js.org/reference/p5.Image/height/"
    },
    {
        "text": "loadPixels()",
        "link": "https://p5js.org/reference/p5.Image/loadPixels/"
    },
    {
        "text": "mask()",
        "link": "https://p5js.org/reference/p5.Image/mask/"
    },
    {
        "text": "numFrames()",
        "link": "https://p5js.org/reference/p5.Image/numFrames/"
    },
    {
        "text": "pause()",
        "link": "https://p5js.org/reference/p5.Image/pause/"
    },
    {
        "text": "pixelDensity()",
        "link": "https://p5js.org/reference/p5.Image/pixelDensity/"
    },
    {
        "text": "pixels",
        "link": "https://p5js.org/reference/p5.Image/pixels/"
    },
    {
        "text": "play()",
        "link": "https://p5js.org/reference/p5.Image/play/"
    },
    {
        "text": "reset()",
        "link": "https://p5js.org/reference/p5.Image/reset/"
    },
    {
        "text": "resize()",
        "link": "https://p5js.org/reference/p5.Image/resize/"
    },
    {
        "text": "save()",
        "link": "https://p5js.org/reference/p5.Image/save/"
    },
    {
        "text": "set()",
        "link": "https://p5js.org/reference/p5.Image/set/"
    },
    {
        "text": "setFrame()",
        "link": "https://p5js.org/reference/p5.Image/setFrame/"
    },
    {
        "text": "updatePixels()",
        "link": "https://p5js.org/reference/p5.Image/updatePixels/"
    },
    {
        "text": "width",
        "link": "https://p5js.org/reference/p5.Image/width/"
    },
    {
        "text": "applyMatrix()",
        "link": "https://p5js.org/reference/p5/applyMatrix/"
    },
    {
        "text": "resetMatrix()",
        "link": "https://p5js.org/reference/p5/resetMatrix/"
    },
    {
        "text": "rotate()",
        "link": "https://p5js.org/reference/p5/rotate/"
    },
    {
        "text": "rotateX()",
        "link": "https://p5js.org/reference/p5/rotateX/"
    },
    {
        "text": "rotateY()",
        "link": "https://p5js.org/reference/p5/rotateY/"
    },
    {
        "text": "rotateZ()",
        "link": "https://p5js.org/reference/p5/rotateZ/"
    },
    {
        "text": "scale()",
        "link": "https://p5js.org/reference/p5/scale/"
    },
    {
        "text": "shearX()",
        "link": "https://p5js.org/reference/p5/shearX/"
    },
    {
        "text": "shearY()",
        "link": "https://p5js.org/reference/p5/shearY/"
    },
    {
        "text": "translate()",
        "link": "https://p5js.org/reference/p5/translate/"
    },
    {
        "text": "cursor()",
        "link": "https://p5js.org/reference/p5/cursor/"
    },
    {
        "text": "deltaTime",
        "link": "https://p5js.org/reference/p5/deltaTime/"
    },
    {
        "text": "describe()",
        "link": "https://p5js.org/reference/p5/describe/"
    },
    {
        "text": "describeElement()",
        "link": "https://p5js.org/reference/p5/describeElement/"
    },
    {
        "text": "displayDensity()",
        "link": "https://p5js.org/reference/p5/displayDensity/"
    },
    {
        "text": "displayHeight",
        "link": "https://p5js.org/reference/p5/displayHeight/"
    },
    {
        "text": "displayWidth",
        "link": "https://p5js.org/reference/p5/displayWidth/"
    },
    {
        "text": "focused",
        "link": "https://p5js.org/reference/p5/focused/"
    },
    {
        "text": "frameCount",
        "link": "https://p5js.org/reference/p5/frameCount/"
    },
    {
        "text": "frameRate()",
        "link": "https://p5js.org/reference/p5/frameRate/"
    },
    {
        "text": "fullscreen()",
        "link": "https://p5js.org/reference/p5/fullscreen/"
    },
    {
        "text": "getTargetFrameRate()",
        "link": "https://p5js.org/reference/p5/getTargetFrameRate/"
    },
    {
        "text": "getURL()",
        "link": "https://p5js.org/reference/p5/getURL/"
    },
    {
        "text": "getURLParams()",
        "link": "https://p5js.org/reference/p5/getURLParams/"
    },
    {
        "text": "getURLPath()",
        "link": "https://p5js.org/reference/p5/getURLPath/"
    },
    {
        "text": "gridOutput()",
        "link": "https://p5js.org/reference/p5/gridOutput/"
    },
    {
        "text": "height",
        "link": "https://p5js.org/reference/p5/height/"
    },
    {
        "text": "noCursor()",
        "link": "https://p5js.org/reference/p5/noCursor/"
    },
    {
        "text": "pixelDensity()",
        "link": "https://p5js.org/reference/p5/pixelDensity/"
    },
    {
        "text": "print()",
        "link": "https://p5js.org/reference/p5/print/"
    },
    {
        "text": "textOutput()",
        "link": "https://p5js.org/reference/p5/textOutput/"
    },
    {
        "text": "webglVersion",
        "link": "https://p5js.org/reference/p5/webglVersion/"
    },
    {
        "text": "width",
        "link": "https://p5js.org/reference/p5/width/"
    },
    {
        "text": "windowHeight",
        "link": "https://p5js.org/reference/p5/windowHeight/"
    },
    {
        "text": "windowResized()",
        "link": "https://p5js.org/reference/p5/windowResized/"
    },
    {
        "text": "windowWidth",
        "link": "https://p5js.org/reference/p5/windowWidth/"
    },
    {
        "text": "camera()",
        "link": "https://p5js.org/reference/p5/camera/"
    },
    {
        "text": "createCamera()",
        "link": "https://p5js.org/reference/p5/createCamera/"
    },
    {
        "text": "frustum()",
        "link": "https://p5js.org/reference/p5/frustum/"
    },
    {
        "text": "linePerspective()",
        "link": "https://p5js.org/reference/p5/linePerspective/"
    },
    {
        "text": "ortho()",
        "link": "https://p5js.org/reference/p5/ortho/"
    },
    {
        "text": "perspective()",
        "link": "https://p5js.org/reference/p5/perspective/"
    },
    {
        "text": "setCamera()",
        "link": "https://p5js.org/reference/p5/setCamera/"
    },
    {
        "text": "debugMode()",
        "link": "https://p5js.org/reference/p5/debugMode/"
    },
    {
        "text": "noDebugMode()",
        "link": "https://p5js.org/reference/p5/noDebugMode/"
    },
    {
        "text": "orbitControl()",
        "link": "https://p5js.org/reference/p5/orbitControl/"
    },
    {
        "text": "ambientLight()",
        "link": "https://p5js.org/reference/p5/ambientLight/"
    },
    {
        "text": "directionalLight()",
        "link": "https://p5js.org/reference/p5/directionalLight/"
    },
    {
        "text": "imageLight()",
        "link": "https://p5js.org/reference/p5/imageLight/"
    },
    {
        "text": "lightFalloff()",
        "link": "https://p5js.org/reference/p5/lightFalloff/"
    },
    {
        "text": "lights()",
        "link": "https://p5js.org/reference/p5/lights/"
    },
    {
        "text": "noLights()",
        "link": "https://p5js.org/reference/p5/noLights/"
    },
    {
        "text": "panorama()",
        "link": "https://p5js.org/reference/p5/panorama/"
    },
    {
        "text": "pointLight()",
        "link": "https://p5js.org/reference/p5/pointLight/"
    },
    {
        "text": "specularColor()",
        "link": "https://p5js.org/reference/p5/specularColor/"
    },
    {
        "text": "spotLight()",
        "link": "https://p5js.org/reference/p5/spotLight/"
    },
    {
        "text": "ambientMaterial()",
        "link": "https://p5js.org/reference/p5/ambientMaterial/"
    },
    {
        "text": "baseColorShader()",
        "link": "https://p5js.org/reference/p5/baseColorShader/"
    },
    {
        "text": "baseMaterialShader()",
        "link": "https://p5js.org/reference/p5/baseMaterialShader/"
    },
    {
        "text": "baseNormalShader()",
        "link": "https://p5js.org/reference/p5/baseNormalShader/"
    },
    {
        "text": "baseStrokeShader()",
        "link": "https://p5js.org/reference/p5/baseStrokeShader/"
    },
    {
        "text": "createFilterShader()",
        "link": "https://p5js.org/reference/p5/createFilterShader/"
    },
    {
        "text": "createShader()",
        "link": "https://p5js.org/reference/p5/createShader/"
    },
    {
        "text": "emissiveMaterial()",
        "link": "https://p5js.org/reference/p5/emissiveMaterial/"
    },
    {
        "text": "loadShader()",
        "link": "https://p5js.org/reference/p5/loadShader/"
    },
    {
        "text": "metalness()",
        "link": "https://p5js.org/reference/p5/metalness/"
    },
    {
        "text": "normalMaterial()",
        "link": "https://p5js.org/reference/p5/normalMaterial/"
    },
    {
        "text": "resetShader()",
        "link": "https://p5js.org/reference/p5/resetShader/"
    },
    {
        "text": "shader()",
        "link": "https://p5js.org/reference/p5/shader/"
    },
    {
        "text": "shininess()",
        "link": "https://p5js.org/reference/p5/shininess/"
    },
    {
        "text": "specularMaterial()",
        "link": "https://p5js.org/reference/p5/specularMaterial/"
    },
    {
        "text": "texture()",
        "link": "https://p5js.org/reference/p5/texture/"
    },
    {
        "text": "textureMode()",
        "link": "https://p5js.org/reference/p5/textureMode/"
    },
    {
        "text": "textureWrap()",
        "link": "https://p5js.org/reference/p5/textureWrap/"
    },
    {
        "text": "camera()",
        "link": "https://p5js.org/reference/p5.Camera/camera/"
    },
    {
        "text": "centerX",
        "link": "https://p5js.org/reference/p5.Camera/centerX/"
    },
    {
        "text": "centerY",
        "link": "https://p5js.org/reference/p5.Camera/centerY/"
    },
    {
        "text": "centerZ",
        "link": "https://p5js.org/reference/p5.Camera/centerZ/"
    },
    {
        "text": "eyeX",
        "link": "https://p5js.org/reference/p5.Camera/eyeX/"
    },
    {
        "text": "eyeY",
        "link": "https://p5js.org/reference/p5.Camera/eyeY/"
    },
    {
        "text": "eyeZ",
        "link": "https://p5js.org/reference/p5.Camera/eyeZ/"
    },
    {
        "text": "frustum()",
        "link": "https://p5js.org/reference/p5.Camera/frustum/"
    },
    {
        "text": "lookAt()",
        "link": "https://p5js.org/reference/p5.Camera/lookAt/"
    },
    {
        "text": "move()",
        "link": "https://p5js.org/reference/p5.Camera/move/"
    },
    {
        "text": "ortho()",
        "link": "https://p5js.org/reference/p5.Camera/ortho/"
    },
    {
        "text": "pan()",
        "link": "https://p5js.org/reference/p5.Camera/pan/"
    },
    {
        "text": "perspective()",
        "link": "https://p5js.org/reference/p5.Camera/perspective/"
    },
    {
        "text": "roll()",
        "link": "https://p5js.org/reference/p5.Camera/roll/"
    },
    {
        "text": "set()",
        "link": "https://p5js.org/reference/p5.Camera/set/"
    },
    {
        "text": "setPosition()",
        "link": "https://p5js.org/reference/p5.Camera/setPosition/"
    },
    {
        "text": "slerp()",
        "link": "https://p5js.org/reference/p5.Camera/slerp/"
    },
    {
        "text": "tilt()",
        "link": "https://p5js.org/reference/p5.Camera/tilt/"
    },
    {
        "text": "upX",
        "link": "https://p5js.org/reference/p5.Camera/upX/"
    },
    {
        "text": "upY",
        "link": "https://p5js.org/reference/p5.Camera/upY/"
    },
    {
        "text": "upZ",
        "link": "https://p5js.org/reference/p5.Camera/upZ/"
    },
    {
        "text": "copyToContext()",
        "link": "https://p5js.org/reference/p5.Shader/copyToContext/"
    },
    {
        "text": "inspectHooks()",
        "link": "https://p5js.org/reference/p5.Shader/inspectHooks/"
    },
    {
        "text": "modify()",
        "link": "https://p5js.org/reference/p5.Shader/modify/"
    },
    {
        "text": "setUniform()",
        "link": "https://p5js.org/reference/p5.Shader/setUniform/"
    },
    {
        "text": "blendMode()",
        "link": "https://p5js.org/reference/p5/blendMode/"
    },
    {
        "text": "clearDepth()",
        "link": "https://p5js.org/reference/p5/clearDepth/"
    },
    {
        "text": "createCanvas()",
        "link": "https://p5js.org/reference/p5/createCanvas/"
    },
    {
        "text": "createFramebuffer()",
        "link": "https://p5js.org/reference/p5/createFramebuffer/"
    },
    {
        "text": "createGraphics()",
        "link": "https://p5js.org/reference/p5/createGraphics/"
    },
    {
        "text": "drawingContext",
        "link": "https://p5js.org/reference/p5/drawingContext/"
    },
    {
        "text": "noCanvas()",
        "link": "https://p5js.org/reference/p5/noCanvas/"
    },
    {
        "text": "resizeCanvas()",
        "link": "https://p5js.org/reference/p5/resizeCanvas/"
    },
    {
        "text": "setAttributes()",
        "link": "https://p5js.org/reference/p5/setAttributes/"
    },
    {
        "text": "autoSized()",
        "link": "https://p5js.org/reference/p5.Framebuffer/autoSized/"
    },
    {
        "text": "begin()",
        "link": "https://p5js.org/reference/p5.Framebuffer/begin/"
    },
    {
        "text": "color",
        "link": "https://p5js.org/reference/p5.Framebuffer/color/"
    },
    {
        "text": "createCamera()",
        "link": "https://p5js.org/reference/p5.Framebuffer/createCamera/"
    },
    {
        "text": "depth",
        "link": "https://p5js.org/reference/p5.Framebuffer/depth/"
    },
    {
        "text": "draw()",
        "link": "https://p5js.org/reference/p5.Framebuffer/draw/"
    },
    {
        "text": "end()",
        "link": "https://p5js.org/reference/p5.Framebuffer/end/"
    },
    {
        "text": "get()",
        "link": "https://p5js.org/reference/p5.Framebuffer/get/"
    },
    {
        "text": "loadPixels()",
        "link": "https://p5js.org/reference/p5.Framebuffer/loadPixels/"
    },
    {
        "text": "pixelDensity()",
        "link": "https://p5js.org/reference/p5.Framebuffer/pixelDensity/"
    },
    {
        "text": "pixels",
        "link": "https://p5js.org/reference/p5.Framebuffer/pixels/"
    },
    {
        "text": "remove()",
        "link": "https://p5js.org/reference/p5.Framebuffer/remove/"
    },
    {
        "text": "resize()",
        "link": "https://p5js.org/reference/p5.Framebuffer/resize/"
    },
    {
        "text": "updatePixels()",
        "link": "https://p5js.org/reference/p5.Framebuffer/updatePixels/"
    },
    {
        "text": "createFramebuffer()",
        "link": "https://p5js.org/reference/p5.Graphics/createFramebuffer/"
    },
    {
        "text": "remove()",
        "link": "https://p5js.org/reference/p5.Graphics/remove/"
    },
    {
        "text": "reset()",
        "link": "https://p5js.org/reference/p5.Graphics/reset/"
    },
    {
        "text": "abs()",
        "link": "https://p5js.org/reference/p5/abs/"
    },
    {
        "text": "ceil()",
        "link": "https://p5js.org/reference/p5/ceil/"
    },
    {
        "text": "constrain()",
        "link": "https://p5js.org/reference/p5/constrain/"
    },
    {
        "text": "dist()",
        "link": "https://p5js.org/reference/p5/dist/"
    },
    {
        "text": "exp()",
        "link": "https://p5js.org/reference/p5/exp/"
    },
    {
        "text": "floor()",
        "link": "https://p5js.org/reference/p5/floor/"
    },
    {
        "text": "fract()",
        "link": "https://p5js.org/reference/p5/fract/"
    },
    {
        "text": "lerp()",
        "link": "https://p5js.org/reference/p5/lerp/"
    },
    {
        "text": "log()",
        "link": "https://p5js.org/reference/p5/log/"
    },
    {
        "text": "mag()",
        "link": "https://p5js.org/reference/p5/mag/"
    },
    {
        "text": "map()",
        "link": "https://p5js.org/reference/p5/map/"
    },
    {
        "text": "max()",
        "link": "https://p5js.org/reference/p5/max/"
    },
    {
        "text": "min()",
        "link": "https://p5js.org/reference/p5/min/"
    },
    {
        "text": "norm()",
        "link": "https://p5js.org/reference/p5/norm/"
    },
    {
        "text": "pow()",
        "link": "https://p5js.org/reference/p5/pow/"
    },
    {
        "text": "round()",
        "link": "https://p5js.org/reference/p5/round/"
    },
    {
        "text": "sq()",
        "link": "https://p5js.org/reference/p5/sq/"
    },
    {
        "text": "sqrt()",
        "link": "https://p5js.org/reference/p5/sqrt/"
    },
    {
        "text": "noise()",
        "link": "https://p5js.org/reference/p5/noise/"
    },
    {
        "text": "noiseDetail()",
        "link": "https://p5js.org/reference/p5/noiseDetail/"
    },
    {
        "text": "noiseSeed()",
        "link": "https://p5js.org/reference/p5/noiseSeed/"
    },
    {
        "text": "random()",
        "link": "https://p5js.org/reference/p5/random/"
    },
    {
        "text": "randomGaussian()",
        "link": "https://p5js.org/reference/p5/randomGaussian/"
    },
    {
        "text": "randomSeed()",
        "link": "https://p5js.org/reference/p5/randomSeed/"
    },
    {
        "text": "acos()",
        "link": "https://p5js.org/reference/p5/acos/"
    },
    {
        "text": "angleMode()",
        "link": "https://p5js.org/reference/p5/angleMode/"
    },
    {
        "text": "asin()",
        "link": "https://p5js.org/reference/p5/asin/"
    },
    {
        "text": "atan()",
        "link": "https://p5js.org/reference/p5/atan/"
    },
    {
        "text": "atan2()",
        "link": "https://p5js.org/reference/p5/atan2/"
    },
    {
        "text": "cos()",
        "link": "https://p5js.org/reference/p5/cos/"
    },
    {
        "text": "degrees()",
        "link": "https://p5js.org/reference/p5/degrees/"
    },
    {
        "text": "radians()",
        "link": "https://p5js.org/reference/p5/radians/"
    },
    {
        "text": "sin()",
        "link": "https://p5js.org/reference/p5/sin/"
    },
    {
        "text": "tan()",
        "link": "https://p5js.org/reference/p5/tan/"
    },
    {
        "text": "createVector()",
        "link": "https://p5js.org/reference/p5/createVector/"
    },
    {
        "text": "add()",
        "link": "https://p5js.org/reference/p5.Vector/add/"
    },
    {
        "text": "angleBetween()",
        "link": "https://p5js.org/reference/p5.Vector/angleBetween/"
    },
    {
        "text": "array()",
        "link": "https://p5js.org/reference/p5.Vector/array/"
    },
    {
        "text": "clampToZero()",
        "link": "https://p5js.org/reference/p5.Vector/clampToZero/"
    },
    {
        "text": "copy()",
        "link": "https://p5js.org/reference/p5.Vector/copy/"
    },
    {
        "text": "cross()",
        "link": "https://p5js.org/reference/p5.Vector/cross/"
    },
    {
        "text": "dist()",
        "link": "https://p5js.org/reference/p5.Vector/dist/"
    },
    {
        "text": "div()",
        "link": "https://p5js.org/reference/p5.Vector/div/"
    },
    {
        "text": "dot()",
        "link": "https://p5js.org/reference/p5.Vector/dot/"
    },
    {
        "text": "equals()",
        "link": "https://p5js.org/reference/p5.Vector/equals/"
    },
    {
        "text": "fromAngle()",
        "link": "https://p5js.org/reference/p5.Vector/fromAngle/"
    },
    {
        "text": "fromAngles()",
        "link": "https://p5js.org/reference/p5.Vector/fromAngles/"
    },
    {
        "text": "heading()",
        "link": "https://p5js.org/reference/p5.Vector/heading/"
    },
    {
        "text": "lerp()",
        "link": "https://p5js.org/reference/p5.Vector/lerp/"
    },
    {
        "text": "limit()",
        "link": "https://p5js.org/reference/p5.Vector/limit/"
    },
    {
        "text": "mag()",
        "link": "https://p5js.org/reference/p5.Vector/mag/"
    },
    {
        "text": "magSq()",
        "link": "https://p5js.org/reference/p5.Vector/magSq/"
    },
    {
        "text": "mult()",
        "link": "https://p5js.org/reference/p5.Vector/mult/"
    },
    {
        "text": "normalize()",
        "link": "https://p5js.org/reference/p5.Vector/normalize/"
    },
    {
        "text": "random2D()",
        "link": "https://p5js.org/reference/p5.Vector/random2D/"
    },
    {
        "text": "random3D()",
        "link": "https://p5js.org/reference/p5.Vector/random3D/"
    },
    {
        "text": "reflect()",
        "link": "https://p5js.org/reference/p5.Vector/reflect/"
    },
    {
        "text": "rem()",
        "link": "https://p5js.org/reference/p5.Vector/rem/"
    },
    {
        "text": "rotate()",
        "link": "https://p5js.org/reference/p5.Vector/rotate/"
    },
    {
        "text": "set()",
        "link": "https://p5js.org/reference/p5.Vector/set/"
    },
    {
        "text": "setHeading()",
        "link": "https://p5js.org/reference/p5.Vector/setHeading/"
    },
    {
        "text": "setMag()",
        "link": "https://p5js.org/reference/p5.Vector/setMag/"
    },
    {
        "text": "slerp()",
        "link": "https://p5js.org/reference/p5.Vector/slerp/"
    },
    {
        "text": "sub()",
        "link": "https://p5js.org/reference/p5.Vector/sub/"
    },
    {
        "text": "toString()",
        "link": "https://p5js.org/reference/p5.Vector/toString/"
    },
    {
        "text": "x",
        "link": "https://p5js.org/reference/p5.Vector/x/"
    },
    {
        "text": "y",
        "link": "https://p5js.org/reference/p5.Vector/y/"
    },
    {
        "text": "z",
        "link": "https://p5js.org/reference/p5.Vector/z/"
    },
    {
        "text": "httpDo()",
        "link": "https://p5js.org/reference/p5/httpDo/"
    },
    {
        "text": "httpGet()",
        "link": "https://p5js.org/reference/p5/httpGet/"
    },
    {
        "text": "httpPost()",
        "link": "https://p5js.org/reference/p5/httpPost/"
    },
    {
        "text": "loadBytes()",
        "link": "https://p5js.org/reference/p5/loadBytes/"
    },
    {
        "text": "loadJSON()",
        "link": "https://p5js.org/reference/p5/loadJSON/"
    },
    {
        "text": "loadStrings()",
        "link": "https://p5js.org/reference/p5/loadStrings/"
    },
    {
        "text": "loadTable()",
        "link": "https://p5js.org/reference/p5/loadTable/"
    },
    {
        "text": "loadXML()",
        "link": "https://p5js.org/reference/p5/loadXML/"
    },
    {
        "text": "createWriter()",
        "link": "https://p5js.org/reference/p5/createWriter/"
    },
    {
        "text": "p5.PrintWriter",
        "link": "https://p5js.org/reference/p5/p5.PrintWriter/"
    },
    {
        "text": "save()",
        "link": "https://p5js.org/reference/p5/save/"
    },
    {
        "text": "saveJSON()",
        "link": "https://p5js.org/reference/p5/saveJSON/"
    },
    {
        "text": "saveStrings()",
        "link": "https://p5js.org/reference/p5/saveStrings/"
    },
    {
        "text": "saveTable()",
        "link": "https://p5js.org/reference/p5/saveTable/"
    },
    {
        "text": "day()",
        "link": "https://p5js.org/reference/p5/day/"
    },
    {
        "text": "hour()",
        "link": "https://p5js.org/reference/p5/hour/"
    },
    {
        "text": "millis()",
        "link": "https://p5js.org/reference/p5/millis/"
    },
    {
        "text": "minute()",
        "link": "https://p5js.org/reference/p5/minute/"
    },
    {
        "text": "month()",
        "link": "https://p5js.org/reference/p5/month/"
    },
    {
        "text": "second()",
        "link": "https://p5js.org/reference/p5/second/"
    },
    {
        "text": "year()",
        "link": "https://p5js.org/reference/p5/year/"
    },
    {
        "text": "addColumn()",
        "link": "https://p5js.org/reference/p5.Table/addColumn/"
    },
    {
        "text": "addRow()",
        "link": "https://p5js.org/reference/p5.Table/addRow/"
    },
    {
        "text": "clearRows()",
        "link": "https://p5js.org/reference/p5.Table/clearRows/"
    },
    {
        "text": "columns",
        "link": "https://p5js.org/reference/p5.Table/columns/"
    },
    {
        "text": "findRow()",
        "link": "https://p5js.org/reference/p5.Table/findRow/"
    },
    {
        "text": "findRows()",
        "link": "https://p5js.org/reference/p5.Table/findRows/"
    },
    {
        "text": "get()",
        "link": "https://p5js.org/reference/p5.Table/get/"
    },
    {
        "text": "getArray()",
        "link": "https://p5js.org/reference/p5.Table/getArray/"
    },
    {
        "text": "getColumn()",
        "link": "https://p5js.org/reference/p5.Table/getColumn/"
    },
    {
        "text": "getColumnCount()",
        "link": "https://p5js.org/reference/p5.Table/getColumnCount/"
    },
    {
        "text": "getNum()",
        "link": "https://p5js.org/reference/p5.Table/getNum/"
    },
    {
        "text": "getObject()",
        "link": "https://p5js.org/reference/p5.Table/getObject/"
    },
    {
        "text": "getRow()",
        "link": "https://p5js.org/reference/p5.Table/getRow/"
    },
    {
        "text": "getRowCount()",
        "link": "https://p5js.org/reference/p5.Table/getRowCount/"
    },
    {
        "text": "getRows()",
        "link": "https://p5js.org/reference/p5.Table/getRows/"
    },
    {
        "text": "getString()",
        "link": "https://p5js.org/reference/p5.Table/getString/"
    },
    {
        "text": "matchRow()",
        "link": "https://p5js.org/reference/p5.Table/matchRow/"
    },
    {
        "text": "matchRows()",
        "link": "https://p5js.org/reference/p5.Table/matchRows/"
    },
    {
        "text": "removeColumn()",
        "link": "https://p5js.org/reference/p5.Table/removeColumn/"
    },
    {
        "text": "removeRow()",
        "link": "https://p5js.org/reference/p5.Table/removeRow/"
    },
    {
        "text": "removeTokens()",
        "link": "https://p5js.org/reference/p5.Table/removeTokens/"
    },
    {
        "text": "rows",
        "link": "https://p5js.org/reference/p5.Table/rows/"
    },
    {
        "text": "set()",
        "link": "https://p5js.org/reference/p5.Table/set/"
    },
    {
        "text": "setNum()",
        "link": "https://p5js.org/reference/p5.Table/setNum/"
    },
    {
        "text": "setString()",
        "link": "https://p5js.org/reference/p5.Table/setString/"
    },
    {
        "text": "trim()",
        "link": "https://p5js.org/reference/p5.Table/trim/"
    },
    {
        "text": "get()",
        "link": "https://p5js.org/reference/p5.TableRow/get/"
    },
    {
        "text": "getNum()",
        "link": "https://p5js.org/reference/p5.TableRow/getNum/"
    },
    {
        "text": "getString()",
        "link": "https://p5js.org/reference/p5.TableRow/getString/"
    },
    {
        "text": "set()",
        "link": "https://p5js.org/reference/p5.TableRow/set/"
    },
    {
        "text": "setNum()",
        "link": "https://p5js.org/reference/p5.TableRow/setNum/"
    },
    {
        "text": "setString()",
        "link": "https://p5js.org/reference/p5.TableRow/setString/"
    },
    {
        "text": "addChild()",
        "link": "https://p5js.org/reference/p5.XML/addChild/"
    },
    {
        "text": "getAttributeCount()",
        "link": "https://p5js.org/reference/p5.XML/getAttributeCount/"
    },
    {
        "text": "getChild()",
        "link": "https://p5js.org/reference/p5.XML/getChild/"
    },
    {
        "text": "getChildren()",
        "link": "https://p5js.org/reference/p5.XML/getChildren/"
    },
    {
        "text": "getContent()",
        "link": "https://p5js.org/reference/p5.XML/getContent/"
    },
    {
        "text": "getName()",
        "link": "https://p5js.org/reference/p5.XML/getName/"
    },
    {
        "text": "getNum()",
        "link": "https://p5js.org/reference/p5.XML/getNum/"
    },
    {
        "text": "getParent()",
        "link": "https://p5js.org/reference/p5.XML/getParent/"
    },
    {
        "text": "getString()",
        "link": "https://p5js.org/reference/p5.XML/getString/"
    },
    {
        "text": "hasAttribute()",
        "link": "https://p5js.org/reference/p5.XML/hasAttribute/"
    },
    {
        "text": "hasChildren()",
        "link": "https://p5js.org/reference/p5.XML/hasChildren/"
    },
    {
        "text": "listAttributes()",
        "link": "https://p5js.org/reference/p5.XML/listAttributes/"
    },
    {
        "text": "listChildren()",
        "link": "https://p5js.org/reference/p5.XML/listChildren/"
    },
    {
        "text": "removeChild()",
        "link": "https://p5js.org/reference/p5.XML/removeChild/"
    },
    {
        "text": "serialize()",
        "link": "https://p5js.org/reference/p5.XML/serialize/"
    },
    {
        "text": "setAttribute()",
        "link": "https://p5js.org/reference/p5.XML/setAttribute/"
    },
    {
        "text": "setContent()",
        "link": "https://p5js.org/reference/p5.XML/setContent/"
    },
    {
        "text": "setName()",
        "link": "https://p5js.org/reference/p5.XML/setName/"
    },
    {
        "text": "accelerationX",
        "link": "https://p5js.org/reference/p5/accelerationX/"
    },
    {
        "text": "accelerationY",
        "link": "https://p5js.org/reference/p5/accelerationY/"
    },
    {
        "text": "accelerationZ",
        "link": "https://p5js.org/reference/p5/accelerationZ/"
    },
    {
        "text": "deviceMoved()",
        "link": "https://p5js.org/reference/p5/deviceMoved/"
    },
    {
        "text": "deviceOrientation",
        "link": "https://p5js.org/reference/p5/deviceOrientation/"
    },
    {
        "text": "deviceShaken()",
        "link": "https://p5js.org/reference/p5/deviceShaken/"
    },
    {
        "text": "deviceTurned()",
        "link": "https://p5js.org/reference/p5/deviceTurned/"
    },
    {
        "text": "pAccelerationX",
        "link": "https://p5js.org/reference/p5/pAccelerationX/"
    },
    {
        "text": "pAccelerationY",
        "link": "https://p5js.org/reference/p5/pAccelerationY/"
    },
    {
        "text": "pAccelerationZ",
        "link": "https://p5js.org/reference/p5/pAccelerationZ/"
    },
    {
        "text": "pRotationX",
        "link": "https://p5js.org/reference/p5/pRotationX/"
    },
    {
        "text": "pRotationY",
        "link": "https://p5js.org/reference/p5/pRotationY/"
    },
    {
        "text": "pRotationZ",
        "link": "https://p5js.org/reference/p5/pRotationZ/"
    },
    {
        "text": "rotationX",
        "link": "https://p5js.org/reference/p5/rotationX/"
    },
    {
        "text": "rotationY",
        "link": "https://p5js.org/reference/p5/rotationY/"
    },
    {
        "text": "rotationZ",
        "link": "https://p5js.org/reference/p5/rotationZ/"
    },
    {
        "text": "setMoveThreshold()",
        "link": "https://p5js.org/reference/p5/setMoveThreshold/"
    },
    {
        "text": "setShakeThreshold()",
        "link": "https://p5js.org/reference/p5/setShakeThreshold/"
    },
    {
        "text": "turnAxis",
        "link": "https://p5js.org/reference/p5/turnAxis/"
    },
    {
        "text": "key",
        "link": "https://p5js.org/reference/p5/key/"
    },
    {
        "text": "keyCode",
        "link": "https://p5js.org/reference/p5/keyCode/"
    },
    {
        "text": "keyIsDown()",
        "link": "https://p5js.org/reference/p5/keyIsDown/"
    },
    {
        "text": "keyIsPressed",
        "link": "https://p5js.org/reference/p5/keyIsPressed/"
    },
    {
        "text": "keyPressed()",
        "link": "https://p5js.org/reference/p5/keyPressed/"
    },
    {
        "text": "keyReleased()",
        "link": "https://p5js.org/reference/p5/keyReleased/"
    },
    {
        "text": "keyTyped()",
        "link": "https://p5js.org/reference/p5/keyTyped/"
    },
    {
        "text": "doubleClicked()",
        "link": "https://p5js.org/reference/p5/doubleClicked/"
    },
    {
        "text": "exitPointerLock()",
        "link": "https://p5js.org/reference/p5/exitPointerLock/"
    },
    {
        "text": "mouseButton",
        "link": "https://p5js.org/reference/p5/mouseButton/"
    },
    {
        "text": "mouseClicked()",
        "link": "https://p5js.org/reference/p5/mouseClicked/"
    },
    {
        "text": "mouseDragged()",
        "link": "https://p5js.org/reference/p5/mouseDragged/"
    },
    {
        "text": "mouseIsPressed",
        "link": "https://p5js.org/reference/p5/mouseIsPressed/"
    },
    {
        "text": "mouseMoved()",
        "link": "https://p5js.org/reference/p5/mouseMoved/"
    },
    {
        "text": "mousePressed()",
        "link": "https://p5js.org/reference/p5/mousePressed/"
    },
    {
        "text": "mouseReleased()",
        "link": "https://p5js.org/reference/p5/mouseReleased/"
    },
    {
        "text": "mouseWheel()",
        "link": "https://p5js.org/reference/p5/mouseWheel/"
    },
    {
        "text": "mouseX",
        "link": "https://p5js.org/reference/p5/mouseX/"
    },
    {
        "text": "mouseY",
        "link": "https://p5js.org/reference/p5/mouseY/"
    },
    {
        "text": "movedX",
        "link": "https://p5js.org/reference/p5/movedX/"
    },
    {
        "text": "movedY",
        "link": "https://p5js.org/reference/p5/movedY/"
    },
    {
        "text": "pmouseX",
        "link": "https://p5js.org/reference/p5/pmouseX/"
    },
    {
        "text": "pmouseY",
        "link": "https://p5js.org/reference/p5/pmouseY/"
    },
    {
        "text": "pwinMouseX",
        "link": "https://p5js.org/reference/p5/pwinMouseX/"
    },
    {
        "text": "pwinMouseY",
        "link": "https://p5js.org/reference/p5/pwinMouseY/"
    },
    {
        "text": "requestPointerLock()",
        "link": "https://p5js.org/reference/p5/requestPointerLock/"
    },
    {
        "text": "winMouseX",
        "link": "https://p5js.org/reference/p5/winMouseX/"
    },
    {
        "text": "winMouseY",
        "link": "https://p5js.org/reference/p5/winMouseY/"
    },
    {
        "text": "touchEnded()",
        "link": "https://p5js.org/reference/p5/touchEnded/"
    },
    {
        "text": "touchMoved()",
        "link": "https://p5js.org/reference/p5/touchMoved/"
    },
    {
        "text": "touchStarted()",
        "link": "https://p5js.org/reference/p5/touchStarted/"
    },
    {
        "text": "touches",
        "link": "https://p5js.org/reference/p5/touches/"
    },
    {
        "text": "changed()",
        "link": "https://p5js.org/reference/p5/changed/"
    },
    {
        "text": "createA()",
        "link": "https://p5js.org/reference/p5/createA/"
    },
    {
        "text": "createAudio()",
        "link": "https://p5js.org/reference/p5/createAudio/"
    },
    {
        "text": "createButton()",
        "link": "https://p5js.org/reference/p5/createButton/"
    },
    {
        "text": "createCapture()",
        "link": "https://p5js.org/reference/p5/createCapture/"
    },
    {
        "text": "createCheckbox()",
        "link": "https://p5js.org/reference/p5/createCheckbox/"
    },
    {
        "text": "createColorPicker()",
        "link": "https://p5js.org/reference/p5/createColorPicker/"
    },
    {
        "text": "createDiv()",
        "link": "https://p5js.org/reference/p5/createDiv/"
    },
    {
        "text": "createElement()",
        "link": "https://p5js.org/reference/p5/createElement/"
    },
    {
        "text": "createFileInput()",
        "link": "https://p5js.org/reference/p5/createFileInput/"
    },
    {
        "text": "createImg()",
        "link": "https://p5js.org/reference/p5/createImg/"
    },
    {
        "text": "createInput()",
        "link": "https://p5js.org/reference/p5/createInput/"
    },
    {
        "text": "createP()",
        "link": "https://p5js.org/reference/p5/createP/"
    },
    {
        "text": "createRadio()",
        "link": "https://p5js.org/reference/p5/createRadio/"
    },
    {
        "text": "createSelect()",
        "link": "https://p5js.org/reference/p5/createSelect/"
    },
    {
        "text": "createSlider()",
        "link": "https://p5js.org/reference/p5/createSlider/"
    },
    {
        "text": "createSpan()",
        "link": "https://p5js.org/reference/p5/createSpan/"
    },
    {
        "text": "createVideo()",
        "link": "https://p5js.org/reference/p5/createVideo/"
    },
    {
        "text": "input()",
        "link": "https://p5js.org/reference/p5/input/"
    },
    {
        "text": "removeElements()",
        "link": "https://p5js.org/reference/p5/removeElements/"
    },
    {
        "text": "select()",
        "link": "https://p5js.org/reference/p5/select/"
    },
    {
        "text": "selectAll()",
        "link": "https://p5js.org/reference/p5/selectAll/"
    },
    {
        "text": "addClass()",
        "link": "https://p5js.org/reference/p5.Element/addClass/"
    },
    {
        "text": "attribute()",
        "link": "https://p5js.org/reference/p5.Element/attribute/"
    },
    {
        "text": "center()",
        "link": "https://p5js.org/reference/p5.Element/center/"
    },
    {
        "text": "child()",
        "link": "https://p5js.org/reference/p5.Element/child/"
    },
    {
        "text": "class()",
        "link": "https://p5js.org/reference/p5.Element/class/"
    },
    {
        "text": "doubleClicked()",
        "link": "https://p5js.org/reference/p5.Element/doubleClicked/"
    },
    {
        "text": "dragLeave()",
        "link": "https://p5js.org/reference/p5.Element/dragLeave/"
    },
    {
        "text": "dragOver()",
        "link": "https://p5js.org/reference/p5.Element/dragOver/"
    },
    {
        "text": "draggable()",
        "link": "https://p5js.org/reference/p5.Element/draggable/"
    },
    {
        "text": "drop()",
        "link": "https://p5js.org/reference/p5.Element/drop/"
    },
    {
        "text": "elt",
        "link": "https://p5js.org/reference/p5.Element/elt/"
    },
    {
        "text": "hasClass()",
        "link": "https://p5js.org/reference/p5.Element/hasClass/"
    },
    {
        "text": "height",
        "link": "https://p5js.org/reference/p5.Element/height/"
    },
    {
        "text": "hide()",
        "link": "https://p5js.org/reference/p5.Element/hide/"
    },
    {
        "text": "html()",
        "link": "https://p5js.org/reference/p5.Element/html/"
    },
    {
        "text": "id()",
        "link": "https://p5js.org/reference/p5.Element/id/"
    },
    {
        "text": "mouseClicked()",
        "link": "https://p5js.org/reference/p5.Element/mouseClicked/"
    },
    {
        "text": "mouseMoved()",
        "link": "https://p5js.org/reference/p5.Element/mouseMoved/"
    },
    {
        "text": "mouseOut()",
        "link": "https://p5js.org/reference/p5.Element/mouseOut/"
    },
    {
        "text": "mouseOver()",
        "link": "https://p5js.org/reference/p5.Element/mouseOver/"
    },
    {
        "text": "mousePressed()",
        "link": "https://p5js.org/reference/p5.Element/mousePressed/"
    },
    {
        "text": "mouseReleased()",
        "link": "https://p5js.org/reference/p5.Element/mouseReleased/"
    },
    {
        "text": "mouseWheel()",
        "link": "https://p5js.org/reference/p5.Element/mouseWheel/"
    },
    {
        "text": "parent()",
        "link": "https://p5js.org/reference/p5.Element/parent/"
    },
    {
        "text": "position()",
        "link": "https://p5js.org/reference/p5.Element/position/"
    },
    {
        "text": "remove()",
        "link": "https://p5js.org/reference/p5.Element/remove/"
    },
    {
        "text": "removeAttribute()",
        "link": "https://p5js.org/reference/p5.Element/removeAttribute/"
    },
    {
        "text": "removeClass()",
        "link": "https://p5js.org/reference/p5.Element/removeClass/"
    },
    {
        "text": "show()",
        "link": "https://p5js.org/reference/p5.Element/show/"
    },
    {
        "text": "size()",
        "link": "https://p5js.org/reference/p5.Element/size/"
    },
    {
        "text": "style()",
        "link": "https://p5js.org/reference/p5.Element/style/"
    },
    {
        "text": "toggleClass()",
        "link": "https://p5js.org/reference/p5.Element/toggleClass/"
    },
    {
        "text": "touchEnded()",
        "link": "https://p5js.org/reference/p5.Element/touchEnded/"
    },
    {
        "text": "touchMoved()",
        "link": "https://p5js.org/reference/p5.Element/touchMoved/"
    },
    {
        "text": "touchStarted()",
        "link": "https://p5js.org/reference/p5.Element/touchStarted/"
    },
    {
        "text": "value()",
        "link": "https://p5js.org/reference/p5.Element/value/"
    },
    {
        "text": "width",
        "link": "https://p5js.org/reference/p5.Element/width/"
    },
    {
        "text": "data",
        "link": "https://p5js.org/reference/p5.File/data/"
    },
    {
        "text": "file",
        "link": "https://p5js.org/reference/p5.File/file/"
    },
    {
        "text": "name",
        "link": "https://p5js.org/reference/p5.File/name/"
    },
    {
        "text": "size",
        "link": "https://p5js.org/reference/p5.File/size/"
    },
    {
        "text": "subtype",
        "link": "https://p5js.org/reference/p5.File/subtype/"
    },
    {
        "text": "type",
        "link": "https://p5js.org/reference/p5.File/type/"
    },
    {
        "text": "addCue()",
        "link": "https://p5js.org/reference/p5.MediaElement/addCue/"
    },
    {
        "text": "autoplay()",
        "link": "https://p5js.org/reference/p5.MediaElement/autoplay/"
    },
    {
        "text": "clearCues()",
        "link": "https://p5js.org/reference/p5.MediaElement/clearCues/"
    },
    {
        "text": "connect()",
        "link": "https://p5js.org/reference/p5.MediaElement/connect/"
    },
    {
        "text": "disconnect()",
        "link": "https://p5js.org/reference/p5.MediaElement/disconnect/"
    },
    {
        "text": "duration()",
        "link": "https://p5js.org/reference/p5.MediaElement/duration/"
    },
    {
        "text": "hideControls()",
        "link": "https://p5js.org/reference/p5.MediaElement/hideControls/"
    },
    {
        "text": "loop()",
        "link": "https://p5js.org/reference/p5.MediaElement/loop/"
    },
    {
        "text": "noLoop()",
        "link": "https://p5js.org/reference/p5.MediaElement/noLoop/"
    },
    {
        "text": "onended()",
        "link": "https://p5js.org/reference/p5.MediaElement/onended/"
    },
    {
        "text": "pause()",
        "link": "https://p5js.org/reference/p5.MediaElement/pause/"
    },
    {
        "text": "play()",
        "link": "https://p5js.org/reference/p5.MediaElement/play/"
    },
    {
        "text": "removeCue()",
        "link": "https://p5js.org/reference/p5.MediaElement/removeCue/"
    },
    {
        "text": "showControls()",
        "link": "https://p5js.org/reference/p5.MediaElement/showControls/"
    },
    {
        "text": "speed()",
        "link": "https://p5js.org/reference/p5.MediaElement/speed/"
    },
    {
        "text": "src",
        "link": "https://p5js.org/reference/p5.MediaElement/src/"
    },
    {
        "text": "stop()",
        "link": "https://p5js.org/reference/p5.MediaElement/stop/"
    },
    {
        "text": "time()",
        "link": "https://p5js.org/reference/p5.MediaElement/time/"
    },
    {
        "text": "volume()",
        "link": "https://p5js.org/reference/p5.MediaElement/volume/"
    },
    {
        "text": "append()",
        "link": "https://p5js.org/reference/p5/append/"
    },
    {
        "text": "arrayCopy()",
        "link": "https://p5js.org/reference/p5/arrayCopy/"
    },
    {
        "text": "concat()",
        "link": "https://p5js.org/reference/p5/concat/"
    },
    {
        "text": "reverse()",
        "link": "https://p5js.org/reference/p5/reverse/"
    },
    {
        "text": "shorten()",
        "link": "https://p5js.org/reference/p5/shorten/"
    },
    {
        "text": "shuffle()",
        "link": "https://p5js.org/reference/p5/shuffle/"
    },
    {
        "text": "sort()",
        "link": "https://p5js.org/reference/p5/sort/"
    },
    {
        "text": "splice()",
        "link": "https://p5js.org/reference/p5/splice/"
    },
    {
        "text": "subset()",
        "link": "https://p5js.org/reference/p5/subset/"
    },
    {
        "text": "boolean()",
        "link": "https://p5js.org/reference/p5/boolean/"
    },
    {
        "text": "byte()",
        "link": "https://p5js.org/reference/p5/byte/"
    },
    {
        "text": "char()",
        "link": "https://p5js.org/reference/p5/char/"
    },
    {
        "text": "float()",
        "link": "https://p5js.org/reference/p5/float/"
    },
    {
        "text": "hex()",
        "link": "https://p5js.org/reference/p5/hex/"
    },
    {
        "text": "int()",
        "link": "https://p5js.org/reference/p5/int/"
    },
    {
        "text": "str()",
        "link": "https://p5js.org/reference/p5/str/"
    },
    {
        "text": "unchar()",
        "link": "https://p5js.org/reference/p5/unchar/"
    },
    {
        "text": "unhex()",
        "link": "https://p5js.org/reference/p5/unhex/"
    },
    {
        "text": "createNumberDict()",
        "link": "https://p5js.org/reference/p5/createNumberDict/"
    },
    {
        "text": "createStringDict()",
        "link": "https://p5js.org/reference/p5/createStringDict/"
    },
    {
        "text": "p5.StringDict",
        "link": "https://p5js.org/reference/p5/p5.StringDict/"
    },
    {
        "text": "clearStorage()",
        "link": "https://p5js.org/reference/p5/clearStorage/"
    },
    {
        "text": "getItem()",
        "link": "https://p5js.org/reference/p5/getItem/"
    },
    {
        "text": "removeItem()",
        "link": "https://p5js.org/reference/p5/removeItem/"
    },
    {
        "text": "storeItem()",
        "link": "https://p5js.org/reference/p5/storeItem/"
    },
    {
        "text": "join()",
        "link": "https://p5js.org/reference/p5/join/"
    },
    {
        "text": "match()",
        "link": "https://p5js.org/reference/p5/match/"
    },
    {
        "text": "matchAll()",
        "link": "https://p5js.org/reference/p5/matchAll/"
    },
    {
        "text": "nf()",
        "link": "https://p5js.org/reference/p5/nf/"
    },
    {
        "text": "nfc()",
        "link": "https://p5js.org/reference/p5/nfc/"
    },
    {
        "text": "nfp()",
        "link": "https://p5js.org/reference/p5/nfp/"
    },
    {
        "text": "nfs()",
        "link": "https://p5js.org/reference/p5/nfs/"
    },
    {
        "text": "split()",
        "link": "https://p5js.org/reference/p5/split/"
    },
    {
        "text": "splitTokens()",
        "link": "https://p5js.org/reference/p5/splitTokens/"
    },
    {
        "text": "trim()",
        "link": "https://p5js.org/reference/p5/trim/"
    },
    {
        "text": "add()",
        "link": "https://p5js.org/reference/p5.NumberDict/add/"
    },
    {
        "text": "div()",
        "link": "https://p5js.org/reference/p5.NumberDict/div/"
    },
    {
        "text": "maxKey()",
        "link": "https://p5js.org/reference/p5.NumberDict/maxKey/"
    },
    {
        "text": "maxValue()",
        "link": "https://p5js.org/reference/p5.NumberDict/maxValue/"
    },
    {
        "text": "minKey()",
        "link": "https://p5js.org/reference/p5.NumberDict/minKey/"
    },
    {
        "text": "minValue()",
        "link": "https://p5js.org/reference/p5.NumberDict/minValue/"
    },
    {
        "text": "mult()",
        "link": "https://p5js.org/reference/p5.NumberDict/mult/"
    },
    {
        "text": "sub()",
        "link": "https://p5js.org/reference/p5.NumberDict/sub/"
    },
    {
        "text": "clear()",
        "link": "https://p5js.org/reference/p5.TypedDict/clear/"
    },
    {
        "text": "create()",
        "link": "https://p5js.org/reference/p5.TypedDict/create/"
    },
    {
        "text": "get()",
        "link": "https://p5js.org/reference/p5.TypedDict/get/"
    },
    {
        "text": "hasKey()",
        "link": "https://p5js.org/reference/p5.TypedDict/hasKey/"
    },
    {
        "text": "print()",
        "link": "https://p5js.org/reference/p5.TypedDict/print/"
    },
    {
        "text": "remove()",
        "link": "https://p5js.org/reference/p5.TypedDict/remove/"
    },
    {
        "text": "saveJSON()",
        "link": "https://p5js.org/reference/p5.TypedDict/saveJSON/"
    },
    {
        "text": "saveTable()",
        "link": "https://p5js.org/reference/p5.TypedDict/saveTable/"
    },
    {
        "text": "set()",
        "link": "https://p5js.org/reference/p5.TypedDict/set/"
    },
    {
        "text": "size()",
        "link": "https://p5js.org/reference/p5.TypedDict/size/"
    },
    {
        "text": "disableFriendlyErrors",
        "link": "https://p5js.org/reference/p5/disableFriendlyErrors/"
    },
    {
        "text": "draw()",
        "link": "https://p5js.org/reference/p5/draw/"
    },
    {
        "text": "isLooping()",
        "link": "https://p5js.org/reference/p5/isLooping/"
    },
    {
        "text": "loop()",
        "link": "https://p5js.org/reference/p5/loop/"
    },
    {
        "text": "noLoop()",
        "link": "https://p5js.org/reference/p5/noLoop/"
    },
    {
        "text": "pop()",
        "link": "https://p5js.org/reference/p5/pop/"
    },
    {
        "text": "preload()",
        "link": "https://p5js.org/reference/p5/preload/"
    },
    {
        "text": "push()",
        "link": "https://p5js.org/reference/p5/push/"
    },
    {
        "text": "redraw()",
        "link": "https://p5js.org/reference/p5/redraw/"
    },
    {
        "text": "remove()",
        "link": "https://p5js.org/reference/p5/remove/"
    },
    {
        "text": "setup()",
        "link": "https://p5js.org/reference/p5/setup/"
    },
    {
        "text": "AUTO",
        "link": "https://p5js.org/reference/p5/AUTO/"
    },
    {
        "text": "DEGREES",
        "link": "https://p5js.org/reference/p5/DEGREES/"
    },
    {
        "text": "HALF_PI",
        "link": "https://p5js.org/reference/p5/HALF_PI/"
    },
    {
        "text": "HSB",
        "link": "https://p5js.org/reference/p5/HSB/"
    },
    {
        "text": "P2D",
        "link": "https://p5js.org/reference/p5/P2D/"
    },
    {
        "text": "PI",
        "link": "https://p5js.org/reference/p5/PI/"
    },
    {
        "text": "QUARTER_PI",
        "link": "https://p5js.org/reference/p5/QUARTER_PI/"
    },
    {
        "text": "RADIANS",
        "link": "https://p5js.org/reference/p5/RADIANS/"
    },
    {
        "text": "TAU",
        "link": "https://p5js.org/reference/p5/TAU/"
    },
    {
        "text": "TWO_PI",
        "link": "https://p5js.org/reference/p5/TWO_PI/"
    },
    {
        "text": "VERSION",
        "link": "https://p5js.org/reference/p5/VERSION/"
    },
    {
        "text": "WEBGL",
        "link": "https://p5js.org/reference/p5/WEBGL/"
    },
    {
        "text": "WEBGL2",
        "link": "https://p5js.org/reference/p5/WEBGL2/"
    },
    {
        "text": "Array",
        "link": "https://p5js.org/reference/p5/Array/"
    },
    {
        "text": "Number",
        "link": "https://p5js.org/reference/p5/Number/"
    },
    {
        "text": "Object",
        "link": "https://p5js.org/reference/p5/Object/"
    },
    {
        "text": "String",
        "link": "https://p5js.org/reference/p5/String/"
    },
    {
        "text": "class",
        "link": "https://p5js.org/reference/p5/class/"
    },
    {
        "text": "console",
        "link": "https://p5js.org/reference/p5/console/"
    },
    {
        "text": "for",
        "link": "https://p5js.org/reference/p5/for/"
    },
    {
        "text": "function",
        "link": "https://p5js.org/reference/p5/function/"
    },
    {
        "text": "if",
        "link": "https://p5js.org/reference/p5/if/"
    },
    {
        "text": "let",
        "link": "https://p5js.org/reference/p5/let/"
    },
    {
        "text": "while",
        "link": "https://p5js.org/reference/p5/while/"
    }
]